Workbook

Sheet Summary
A1: Tsuji — cost overview
A2: All figures in €. Green = pulled from another sheet. Status: student self-employed (étudiant-indépendant), VAT-exempt while eligible.
A4: Prices (VAT included)
A5: Pro – monthly / annual | B5: =Assumptions!$B$10 -> 4.99 | C5: =Assumptions!$B$11 -> 49.99
A6: Max – monthly / annual | B6: =Assumptions!$B$12 -> 7.99 | C6: =Assumptions!$B$13 -> 59.99
A8: To start (one-off)
A9: Start-up costs – required items, expected | B9: ='Start-up costs'!$I$23 -> 979.327
A10: Start-up costs – including optional items (EU trademark, Mac, marketing…) | B10: ='Start-up costs'!$I$24 -> 3729.327
A12: Fixed costs per month
A13: Launch stage | B13: ='Fixed costs'!$I$24 -> 232.68245
A14: Growth stage | B14: ='Fixed costs'!$J$24 -> 355.32145
A15: Scale stage | B15: ='Fixed costs'!$K$24 -> 736.5767
A16: First 12 months before any revenue (start-up + 12 × Launch) | B16: ='Start-up costs'!$I$23+12*'Fixed costs'!$I$24 -> 3771.5164
A18: Per subscriber, per month (after VAT, fees, LLM, infrastructure)
A19: Pro – contribution margin (blended monthly/annual) | B19: ='Unit economics'!$O$11 -> 1.9976421
A20: Max – contribution margin (blended) | B20: ='Unit economics'!$O$12 -> 3.4058055
A21: All payers – contribution margin | B21: ='Unit economics'!$O$13 -> 2.2536718
A22: All payers – margin, worst-case LLM | B22: ='Unit economics'!$R$13 -> -0.044162172
A23: One free user – variable cost (infrastructure and AI) | B23: ='Unit economics'!$C$29 -> 0.030812
A25: Break-even at the Launch stage (conservative, with VAT on web sales)
A26: Paying users needed | B26: ='Unit economics'!$D$23 -> 100
A27: Active users needed (at the assumed conversion) | B27: ='Unit economics'!$E$23 -> 1801
A29: Projection (from the 'Projection' sheet)
A30: Active users | B30: =Projection!B5 -> 100 | C30: =Projection!C5 -> 500 | D30: =Projection!D5 -> 1000 | E30: =Projection!E5 -> 2500 | F30: =Projection!F5 -> 5000 | G30: =Projection!G5 -> 10000 | H30: =Projection!H5 -> 25000 | I30: =Projection!I5 -> 50000
A31: Net revenue / month | B31: =Projection!B18 -> 19.815322 | C31: =Projection!C18 -> 96.969656 | D31: =Projection!D18 -> 191.41595 | E31: =Projection!E18 -> 476.86179 | F31: =Projection!F18 -> 954.13999 | G31: =Projection!G18 -> 1905.3402 | H31: =Projection!H18 -> 4426.6797 | I31: =Projection!I18 -> 8850.4196
A32: Total costs / month | B32: =Projection!B29 -> 237.56145 | C32: =Projection!C29 -> 256.53716 | D32: =Projection!D29 -> 280.12172 | E32: =Projection!E29 -> 474.0547 | F32: =Projection!F29 -> 592.5178 | G32: =Projection!G29 -> 829.71415 | H32: =Projection!H29 -> 1922.5584 | I32: =Projection!I29 -> 3108.5402
A33: Social contributions / month | B33: =Projection!B34 -> 0 | C33: =Projection!C34 -> 0 | D33: =Projection!D34 -> 0 | E33: =Projection!E34 -> 0 | F33: =Projection!F34 -> 0 | G33: =Projection!G34 -> 72.099741 | H33: =Projection!H34 -> 513.34485 | I33: =Projection!I34 -> 1177.0853
A34: Result after social contributions / month | B34: =Projection!B35 -> -217.74613 | C34: =Projection!C35 -> -159.5675 | D34: =Projection!D35 -> -88.705769 | E34: =Projection!E35 -> 2.8070893 | F34: =Projection!F35 -> 361.62219 | G34: =Projection!G35 -> 1003.5263 | H34: =Projection!H35 -> 1990.7764 | I34: =Projection!I35 -> 4564.7941
A35: VAT exemption applies? (1 = yes) | B35: =Projection!B23 -> 1 | C35: =Projection!C23 -> 1 | D35: =Projection!D23 -> 1 | E35: =Projection!E23 -> 1 | F35: =Projection!F23 -> 1 | G35: =Projection!G23 -> 1 | H35: =Projection!H23 -> 0 | I35: =Projection!I23 -> 0
A36: Still within the student status? | B36: =Projection!B37 -> yes | C36: =Projection!C37 -> yes | D36: =Projection!D37 -> yes | E36: =Projection!E37 -> yes | F36: =Projection!F37 -> yes | G36: =Projection!G37 -> yes | H36: =Projection!H37 -> no: full-time rates | I36: =Projection!I37 -> no: full-time rates
A37: Cost per active user / month | B37: =Projection!B40 -> 2.3756145 | C37: =Projection!C40 -> 0.51307432 | D37: =Projection!D40 -> 0.28012172 | E37: =Projection!E40 -> 0.18962188 | F37: =Projection!F40 -> 0.11850356 | G37: =Projection!G40 -> 0.082971415 | H37: =Projection!H40 -> 0.076902338 | I37: =Projection!I40 -> 0.062170804
A38: Cost per paying user / month | B38: =Projection!B41 -> 39.593575 | C38: =Projection!C41 -> 9.1620414 | D38: =Projection!D41 -> 5.0931222 | E38: =Projection!E41 -> 3.435179 | F38: =Projection!F41 -> 2.1546102 | G38: =Projection!G41 -> 1.5085712 | H38: =Projection!H41 -> 1.3982243 | I38: =Projection!I41 -> 1.1303783
A40: Where we are, and the end-2026 goal
A41: Active users today (early access) | B41: =Assumptions!$B$59 -> 25
A42: Active users needed to break even (Launch stage) | B42: ='Unit economics'!$E$23 -> 1801
A43: … growth needed from today | B43: =IF(OR(B41=0,NOT(ISNUMBER(B42))),0,B42/B41) -> 72.04
A44: Days left to the target date | B44: =MAX(0,Assumptions!$B$60-TODAY()) -> 66
A45: Active users to add per day to get there | B45: =IF(OR(B44=0,NOT(ISNUMBER(B42))),0,(B42-B41)/B44) -> 26.909091

Sheet Assumptions
A1: Assumptions
A2: Blue = input you can change · yellow = key assumption to check · every other sheet reads from here.
A4: Parameter | B4: Value | C4: Unit | D4: Source / note
A5: General
A6: Exchange rate USD → EUR | B6: 0.86 | C6: € per $ | D6: Most providers bill in USD. Set to the current rate.
A7: VAT rate on consumer sales | B7: 0.21 | C7: % | D7: Belgium 21%. Buyers elsewhere in the EU pay their country's rate through the OSS (FR 20%, DE 19%...). Prices are VAT-inclusive.
A8: VAT you pay on services bought abroad, and can't deduct | B8: 0.21 | C8: % | D8: Under the small-business VAT exemption you can't deduct VAT. Services from outside Belgium (Render, Vercel, Supabase, Google AI, Apple...) are taxed through the reverse charge at 21% and cost 21% more. Set to 0% once you register for VAT normally. Check this with your accountant.
A9: Prices (VAT included) – see the 'Pricing' sheet
A10: Pro – monthly | B10: 4.99 | C10: € / month | D10: Owner's decision, 26 Oct 2026 (new monetisation strategy). Previous proposal €8.99; first grid €8.
A11: Pro – annual | B11: 49.99 | C11: € / year | D11: Owner's decision, 26 Oct 2026. Previous proposal €59.99. Saves 17% against 12 × monthly ('Pricing').
A12: Max – monthly | B12: 7.99 | C12: € / month | D12: Owner's decision, 26 Oct 2026. Previous proposal €14.99.
A13: Max – annual | B13: 59.99 | C13: € / year | D13: Owner's decision, 26 Oct 2026. Previous proposal €99.99. Only €10 a year above Pro annual ('Pricing').
A14: Who pays, and how
A15: Share of active users on Pro | B15: 0.045 | C15: % of MAU | D15: Freemium language apps typically convert 2–8% of active users. Replace with real data after launch.
A16: Share of active users on Max | B16: 0.01 | C16: % of MAU | D16: Max is sold mainly as an upgrade when a Pro user reaches a limit. With Max annual only €10 above Pro annual, more payers may pick Max: re-check with real data.
A17: Share of Pro payers on the annual plan | B17: 0.7 | C17: % of Pro payers | D17: The goal: most Pro buyers choose the annual plan (pre-selected, '€5 a month', trial on annual only).
A18: Share of Max payers on the annual plan | B18: 0.45 | C18: % of Max payers | D18: Upgrades from Pro annual go to annual; upgrades from Pro monthly go to monthly.
A19: Share bought through the App Store / Google Play | B19: 0.6 | C19: % of payers | D19: The rest is bought on the web (Stripe). Selling the annual plan on the landing page avoids the commission.
A20: Payment fees
A21: App Store / Google Play commission | B21: 0.15 | C21: % of price excl. VAT | D21: 15% under the Small Business Programs (< $1M/yr) and on every subscription after its first year; 30% otherwise. Stores collect and remit VAT for you.
A22: Stripe card fee (EEA cards) | B22: 0.015 | C22: % of charge | D22: Stripe Belgium standard EEA cards: 1.5% + €0.25.
A23: Stripe fixed fee per charge | B23: 0.25 | C23: € / charge | D23: Paid on every monthly renewal, once a year on annual plans.
A24: Stripe Billing (subscriptions) | B24: 0.007 | C24: % of charge | D24: Stripe Billing pay-as-you-go.
A25: Small-business VAT exemption (franchise regime)
A26: Use the VAT exemption while you're eligible (Y/N) | B26: Y | C26: Y / N | D26: Web buyers are then charged no VAT and you keep the whole price. The stores still apply VAT (they are the seller in-app).
A27: Annual turnover limit for the exemption | B27: 25000 | C27: € / year | D27: Belgian small-business exemption limit.
A28: Limit for web sales to consumers in other EU countries | B28: 10000 | C28: € / year | D28: Above this, buyers abroad pay their own country's VAT (e.g. 20% in France) even if you're exempt in Belgium. Tsuji is French-first, so this limit comes first.
A29: Share of web buyers outside Belgium | B29: 0.8 | C29: % of web sales | D29: Assumption: mostly French-speaking buyers in France.
A30: Variable cost per user per month
A31: LLM cost – Pro user, expected | B31: 0.27 | C31: $ / month | D31: scripts/llm_cost_model.py --fleet: Gemini 3.1 Flash-Lite, 70% light / 25% typical / 5% heavy, with caching. The free Explain button is included (phrase analysis, mostly cached).
A32: LLM cost – Pro user, worst case | B32: ='AI worst case'!$L$26 -> 2.4 | C32: $ / month | D32: From 'AI worst case' (full-price tier): every AI allowance used to the full, every day.
A33: LLM cost – Max user, expected | B33: 0.44 | C33: $ / month | D33: llm_cost_model.py 'typical' user: Max buyers use the app more.
A34: LLM cost – Max user, worst case | B34: ='AI worst case'!$M$26 -> 3 | C34: $ / month | D34: From 'AI worst case' (full-price tier): every AI allowance used to the full, every day.
A35: Variable infrastructure – free user | B35: 0.01 | C35: € / month | D35: Database, auth and bandwidth beyond what the fixed plans include.
A36: Variable infrastructure – paying user | B36: 0.02 | C36: € / month | D36: More audio, practice logs and analyser history.
A37: Stages (which fixed-cost column applies)
A38: Growth stage starts at | B38: 2000 | C38: active users | D38: Bigger Render/Supabase plans, paid e-mail. See 'Fixed costs'.
A39: Scale stage starts at | B39: 20000 | C39: active users
A40: Social contributions – student self-employed (étudiant-indépendant), 2026
A41: No contributions up to | B41: 8687.04 | C41: € net profit / year | D41: Below this taxable profit you owe nothing (2026, UCM / Liantis / Partena).
A42: Student status limit | B42: 17374.08 | C42: € net profit / year | D42: Between the two limits: 20.5% of the part above €8,687.04. At or above this one you pay as a full-time self-employed person.
A43: Contribution rate | B43: 0.205 | C43: % | D43: 20.5% (applies up to ≈ €75k a year; the lower rate above that isn't modelled).
A44: Full-time self-employed minimum, per quarter | B44: 925.59 | C44: € / quarter | D44: Applies once profit reaches the student status limit (2026; sources give €917.58–925.59, check with your fund).
A46: Not modelled: income tax (IPP). Everything here is before income tax. Student self-employed status: 18–25 years old, enrolled for at least 27 credits, proof sent to your fund every year.
A48: Free plan, trial, founder offer, credit packs (new strategy, Oct 2026)
A49: LLM cost – free user, expected | B49: 0.02 | C49: $ / month | D49: Free now has small AI allowances ('AI worst case'). Most free users use few of them and most of what they ask is served from caches and pools. Estimate: replace with scripts/llm_usage_report.py.
A50: LLM cost – free user, worst case | B50: ='AI worst case'!$K$26 -> 0.3 | C50: $ / month | D50: From 'AI worst case': every free allowance used to the full, every day.
A51: Trial (7 days, annual plans only): share of trials that convert | B51: 0.4 | C51: % of trials | D51: Store trials that ask for a payment method commonly convert 30–60%. Replace with real data.
A52: Founder offer: discount on the first year of an annual plan | B52: 0.3 | C52: % | D52: Proposal: −30% on the first year for early-access members (Pro €34.99, Max €41.99). 'Pricing' shows what it does to the worst case.
A53: Founder offer: share of annual payers in their founder year | B53: 1 | C53: % of annual payers | D53: 1 while the offer is open (the end-2026 goal sits inside it). Set to 0 for the steady state once the offer has closed and its first year has run out.
A54: Credit packs: share of free active users buying a pack in a month | B54: 0.01 | C54: % of free MAU | D54: Guess. Packs are bought by free learners who run out and want to go on today.
A55: Credit packs: share of Pro subscribers buying a pack in a month | B55: 0.05 | C55: % of Pro | D55: Pro learners who run past their 120 a day. Max never buys (unlimited, shop hidden).
A56: Credit packs: packs bought per buyer per month | B56: 1.2 | C56: packs | D56: Guess.
A57: Credit packs: average pack price paid | B57: ='Credit shop'!$C$21 -> 3.39 | C57: € (VAT incl.) | D57: From 'Credit shop': the four packs weighted by their sales mix.
A58: Credit packs: share bought in-app | B58: 0.9 | C58: % of packs | D58: An impulse buy inside the app; few go to the web for it.
A59: Early access today: active users | B59: 25 | C59: MAU | D59: Owner, 26 Oct 2026: about 100 sign-ups, 20–30 active.
A60: Target date for break-even | B60: 46387 | C60: date | D60: Owner's goal: profitable by the end of 2026.

Sheet Pricing
A1: Pricing: pushing the annual Pro plan, with Max as the upgrade
A2: Old prices are your first grid; full prices come from Assumptions (change them there); regional prices are at the bottom.
A4: Plan | B4: Billing | C4: Previous proposal (€) | D4: Full price, tier 1 (€) | E4: Per month (€) | F4: Saving vs monthly | G4: Change vs previous | H4: Store price point?
A5: Pro | B5: Monthly | C5: 8.99 | D5: =Assumptions!$B$10 -> 4.99 | E5: =D5/1 -> 4.99 | G5: =D5/C5-1 -> -0.44493882 | H5: =IF(MOD(ROUND(D5*100,0),100)=99,"yes","round to .99") -> yes
A6: Pro | B6: Annual | C6: 59.99 | D6: =Assumptions!$B$11 -> 49.99 | E6: =D6/12 -> 4.1658333 | F6: =1-D6/(12*D5) -> 0.16516366 | G6: =D6/C6-1 -> -0.16669445 | H6: =IF(MOD(ROUND(D6*100,0),100)=99,"yes","round to .99") -> yes
A7: Max | B7: Monthly | C7: 14.99 | D7: =Assumptions!$B$12 -> 7.99 | E7: =D7/1 -> 7.99 | G7: =D7/C7-1 -> -0.46697799 | H7: =IF(MOD(ROUND(D7*100,0),100)=99,"yes","round to .99") -> yes
A8: Max | B8: Annual | C8: 99.99 | D8: =Assumptions!$B$13 -> 59.99 | E8: =D8/12 -> 4.9991667 | F8: =1-D8/(12*D7) -> 0.37432207 | G8: =D8/C8-1 -> -0.40004 | H8: =IF(MOD(ROUND(D8*100,0),100)=99,"yes","round to .99") -> yes
A10: Upgrade to Max
A11: From Pro annual to Max annual, per year | D11: =D8-D6 -> 10 | E11: =IF(D11<0.5*D6,"Max annual is close to Pro annual: most annual buyers will take Max","") -> Max annual is close to Pro annual: most annual buyers will take Max
A12: … per month | D12: =(D8-D6)/12 -> 0.83333333
A13: From Pro monthly to Max monthly, per month | D13: =D7-D5 -> 3
A14: Charge only the difference for the months left (proration): the stores do it automatically for upgrades within a subscription group, and so does Stripe.
A16: Competitors (list prices, USD)
A17: App | B17: What it covers | C17: Monthly ($) | D17: Annual ($) | E17: Lifetime ($) | H17: Source
A18: WaniKani | B18: Kanji and vocabulary only | C18: 9 | D18: 89 | E18: 299 | H18: wanilog.com, 2026
A19: Bunpro | B19: Grammar only | C19: 5 | D19: — | E19: 150 | H19: languavibe.com, May 2026
A20: Renshuu Pro | B20: Vocab, kanji, grammar | C20: 6.99 | D20: 49.99 | E20: 109.99 | H20: App Store listing, 2026
A21: WaniKani + Bunpro | B21: What Tsuji Pro replaces | C21: 14 | D21: — | E21: — | H21: Sum of the two monthly prices
A23: Why these prices
A24: 1 | B24: Pro €4.99 / €49.99 (owner's decision, Oct 2026): a low entry price, the strategy's 'learn well for little'. Annual saves only 17% against 12 × monthly: a weak reason to commit for a year.
A25: 2 | B25: Max €7.99 / €59.99: annual saves 37% and costs only €10 a year more than Pro annual. Side by side, Max annual is the obvious pick and Pro annual a decoy. Either that is the intent (more per payer, thinner worst case) or Pro annual moves (e.g. €39.99, −33%).
A26: 3 | B26: Both plans hold their worst case only through the global AI ceiling a day ('AI worst case'): the per-feature caps alone add up to more than either price carries.
A27: 4 | B27: Max 'unlimited' covers everything paid in credits. The AI features keep fair-use caps and a ceiling, published as such.
A28: 5 | B28: All four prices are standard App Store / Google Play price points (x.99).
A29: 6 | B29: 7-day free trial on the annual plans only, and the founder offer (below) for early-access members.
A30: 7 | B30: Sell the annual plans on the web too (landing page, Stripe). In-app you keep about 70% of the price; on the web, VAT-exempt, about 97%. The founder offer holds its worst case only on the web.
A31: 8 | B31: Re-check after launch: conversion, the annual share, the Pro/Max split, how many reach a cap or the ceiling. Change them in Assumptions.
A33: Regional prices, by purchasing power
A34: Tier | B34: Countries (examples) | C34: Share of payers | D34: Pro price & AI multiplier | E34: Max price & AI multiplier | F34: Pro monthly (€) | G34: Pro annual (€) | H34: Max monthly (€) | I34: Max annual (€) | J34: Pro monthly: worst-case margin/mo (€) | K34: Pro annual: worst-case margin/mo (€) | L34: Max monthly: worst-case margin/mo (€) | M34: Max annual: worst-case margin/mo (€) | N34: Every plan covers its worst case?
A35: 1 – Full price | B35: Belgium, France, Switzerland, Luxembourg, Germany, Netherlands, Nordics, UK, US, Canada, Australia, Japan | C35: 0.7 | D35: 1 | E35: 1 | F35: =MAX(0.99,CEILING(Assumptions!$B$10*D35,1)-0.01) -> 4.99 | G35: =MAX(0.99,CEILING(Assumptions!$B$11*D35,1)-0.01) -> 49.99 | H35: =MAX(0.99,CEILING(Assumptions!$B$12*E35,1)-0.01) -> 7.99 | I35: =MAX(0.99,CEILING(Assumptions!$B$13*E35,1)-0.01) -> 59.99 | J35: =MIN(F35/1/(1+Assumptions!$B$7)*(1-Assumptions!$B$21),(F35/(1+Assumptions!$B$7)-(F35*(Assumptions!$B$22+Assumptions!$B$24)+Assumptions!$B$23))/1)-'AI worst case'!$F$33-Assumptions!$B$36 -> 0.9879319 | K35: =MIN(G35/12/(1+Assumptions!$B$7)*(1-Assumptions!$B$21),(G35/(1+Assumptions!$B$7)-(G35*(Assumptions!$B$22+Assumptions!$B$24)+Assumptions!$B$23))/12)-'AI worst case'!$F$33-Assumptions!$B$36 -> 0.40897185 | L35: =MIN(H35/1/(1+Assumptions!$B$7)*(1-Assumptions!$B$21),(H35/(1+Assumptions!$B$7)-(H35*(Assumptions!$B$22+Assumptions!$B$24)+Assumptions!$B$23))/1)-'AI worst case'!$G$33-Assumptions!$B$36 -> 2.4710099 | M35: =MIN(I35/12/(1+Assumptions!$B$7)*(1-Assumptions!$B$21),(I35/(1+Assumptions!$B$7)-(I35*(Assumptions!$B$22+Assumptions!$B$24)+Assumptions!$B$23))/12)-'AI worst case'!$G$33-Assumptions!$B$36 -> 0.37001129 | N35: =IF(MIN(J35:M35)>='AI worst case'!$B$10,"yes","NO: raise the price or lower the allowance") -> yes
A36: 2 – Reduced | B36: Spain, Italy, Portugal, Greece, Poland, Czechia, the Baltics, Korea, Taiwan | C36: 0.15 | D36: 0.75 | E36: 0.75 | F36: =MAX(0.99,CEILING(Assumptions!$B$10*D36,1)-0.01) -> 3.99 | G36: =MAX(0.99,CEILING(Assumptions!$B$11*D36,1)-0.01) -> 37.99 | H36: =MAX(0.99,CEILING(Assumptions!$B$12*E36,1)-0.01) -> 5.99 | I36: =MAX(0.99,CEILING(Assumptions!$B$13*E36,1)-0.01) -> 44.99 | J36: =MIN(F36/1/(1+Assumptions!$B$7)*(1-Assumptions!$B$21),(F36/(1+Assumptions!$B$7)-(F36*(Assumptions!$B$22+Assumptions!$B$24)+Assumptions!$B$23))/1)-'AI worst case'!$F$34-Assumptions!$B$36 -> 0.93998736 | K36: =MIN(G36/12/(1+Assumptions!$B$7)*(1-Assumptions!$B$21),(G36/(1+Assumptions!$B$7)-(G36*(Assumptions!$B$22+Assumptions!$B$24)+Assumptions!$B$23))/12)-'AI worst case'!$F$34-Assumptions!$B$36 -> 0.36102731 | L36: =MIN(H36/1/(1+Assumptions!$B$7)*(1-Assumptions!$B$21),(H36/(1+Assumptions!$B$7)-(H36*(Assumptions!$B$22+Assumptions!$B$24)+Assumptions!$B$23))/1)-'AI worst case'!$G$34-Assumptions!$B$36 -> 1.8465012 | M36: =MIN(I36/12/(1+Assumptions!$B$7)*(1-Assumptions!$B$21),(I36/(1+Assumptions!$B$7)-(I36*(Assumptions!$B$22+Assumptions!$B$24)+Assumptions!$B$23))/12)-'AI worst case'!$G$34-Assumptions!$B$36 -> 0.27236212 | N36: =IF(MIN(J36:M36)>='AI worst case'!$B$10,"yes","NO: raise the price or lower the allowance") -> yes
A37: 3 – Low | B37: Morocco, Algeria, Tunisia, Turkey, Romania, Brazil, Mexico, Southeast Asia | C37: 0.1 | D37: 0.55 | E37: 0.55 | F37: =MAX(0.99,CEILING(Assumptions!$B$10*D37,1)-0.01) -> 2.99 | G37: =MAX(0.99,CEILING(Assumptions!$B$11*D37,1)-0.01) -> 27.99 | H37: =MAX(0.99,CEILING(Assumptions!$B$12*E37,1)-0.01) -> 4.99 | I37: =MAX(0.99,CEILING(Assumptions!$B$13*E37,1)-0.01) -> 32.99 | J37: =MIN(F37/1/(1+Assumptions!$B$7)*(1-Assumptions!$B$21),(F37/(1+Assumptions!$B$7)-(F37*(Assumptions!$B$22+Assumptions!$B$24)+Assumptions!$B$23))/1)-'AI worst case'!$F$35-Assumptions!$B$36 -> 0.73301573 | K37: =MIN(G37/12/(1+Assumptions!$B$7)*(1-Assumptions!$B$21),(G37/(1+Assumptions!$B$7)-(G37*(Assumptions!$B$22+Assumptions!$B$24)+Assumptions!$B$23))/12)-'AI worst case'!$F$35-Assumptions!$B$36 -> 0.27113556 | L37: =MIN(H37/1/(1+Assumptions!$B$7)*(1-Assumptions!$B$21),(H37/(1+Assumptions!$B$7)-(H37*(Assumptions!$B$22+Assumptions!$B$24)+Assumptions!$B$23))/1)-'AI worst case'!$G$35-Assumptions!$B$36 -> 1.7683819 | M37: =MIN(I37/12/(1+Assumptions!$B$7)*(1-Assumptions!$B$21),(I37/(1+Assumptions!$B$7)-(I37*(Assumptions!$B$22+Assumptions!$B$24)+Assumptions!$B$23))/12)-'AI worst case'!$G$35-Assumptions!$B$36 -> 0.19424278 | N37: =IF(MIN(J37:M37)>='AI worst case'!$B$10,"yes","NO: raise the price or lower the allowance") -> yes
A38: 4 – Lowest | B38: Senegal, Côte d'Ivoire, Cameroon and French-speaking Africa, India, Egypt | C38: 0.05 | D38: 0.45 | E38: 0.45 | F38: =MAX(0.99,CEILING(Assumptions!$B$10*D38,1)-0.01) -> 2.99 | G38: =MAX(0.99,CEILING(Assumptions!$B$11*D38,1)-0.01) -> 22.99 | H38: =MAX(0.99,CEILING(Assumptions!$B$12*E38,1)-0.01) -> 3.99 | I38: =MAX(0.99,CEILING(Assumptions!$B$13*E38,1)-0.01) -> 26.99 | J38: =MIN(F38/1/(1+Assumptions!$B$7)*(1-Assumptions!$B$21),(F38/(1+Assumptions!$B$7)-(F38*(Assumptions!$B$22+Assumptions!$B$24)+Assumptions!$B$23))/1)-'AI worst case'!$F$36-Assumptions!$B$36 -> 1.1374423 | K38: =MIN(G38/12/(1+Assumptions!$B$7)*(1-Assumptions!$B$21),(G38/(1+Assumptions!$B$7)-(G38*(Assumptions!$B$22+Assumptions!$B$24)+Assumptions!$B$23))/12)-'AI worst case'!$F$36-Assumptions!$B$36 -> 0.38286243 | L38: =MIN(H38/1/(1+Assumptions!$B$7)*(1-Assumptions!$B$21),(H38/(1+Assumptions!$B$7)-(H38*(Assumptions!$B$22+Assumptions!$B$24)+Assumptions!$B$23))/1)-'AI worst case'!$G$36-Assumptions!$B$36 -> 1.3780826 | M38: =MIN(I38/12/(1+Assumptions!$B$7)*(1-Assumptions!$B$21),(I38/(1+Assumptions!$B$7)-(I38*(Assumptions!$B$22+Assumptions!$B$24)+Assumptions!$B$23))/12)-'AI worst case'!$G$36-Assumptions!$B$36 -> 0.15518311 | N38: =IF(MIN(J38:M38)>='AI worst case'!$B$10,"yes","NO: raise the price or lower the allowance") -> yes
A39: Average price paid (index) | C39: =SUM(C35:C38) -> 1 | D39: =IF(C39=0,1,SUMPRODUCT(C35:C38,D35:D38)/C39) -> 0.89 | E39: =IF(C39=0,1,SUMPRODUCT(C35:C38,E35:E38)/C39) -> 0.89
A41: The rule: in every tier, even a subscriber using every AI allowance to the full every day must still bring in more than they cost. The margins above are that case, in the channel that keeps least (in-app or web).
A42: The multiplier sets both the price and the AI caps and ceiling in that tier: pay 45% of the price, get 45% of the AI. Reviews, the dictionary and the credits are the same everywhere; they cost almost nothing.
A43: The global AI ceiling is what lets tier 4 hold: without it the per-feature caps alone would cost more than a tier-4 plan brings in.
A44: Which price applies: the store account's country in-app (Apple and Google set prices per country); on the web, the country of the card (Stripe), so a VPN doesn't unlock a cheaper price.
A45: Outside the EU the stores add the local sales tax (e.g. India 18%). The margins use the EU rate as an approximation.
A46: 'Unit economics' and 'Projection' use the average indexes, so revenue already reflects regional prices. The shares of payers must add up to 100%.
A48: Founder offer (early-access members): the first year of an annual plan, full allowances
A49: Plan | B49: Full price (€/yr) | C49: Founder price (€/yr) | D49: Worst-case margin in-app (€/mo) | E49: Worst-case margin on the web, VAT-exempt (€/mo) | F49: Holds in-app? | G49: Holds on the web?
A50: Pro | B50: =$D$6 -> 49.99 | C50: =MAX(0.99,CEILING($D$6*(1-Assumptions!$B$52),1)-0.01) -> 34.99 | D50: =C50/12/(1+Assumptions!$B$7)*(1-Assumptions!$B$21)-'AI worst case'!$F$33-Assumptions!$B$36 -> -0.46912733 | E50: =(C50-(C50*(Assumptions!$B$22+Assumptions!$B$24)+Assumptions!$B$23))/12-'AI worst case'!$F$33-Assumptions!$B$36 -> 0.31341167 | F50: =IF(D50>='AI worst case'!$B$10,"yes","NO") -> NO | G50: =IF(E50>='AI worst case'!$B$10,"yes","NO") -> yes
A51: Max | B51: =$D$8 -> 59.99 | C51: =MAX(0.99,CEILING($D$8*(1-Assumptions!$B$52),1)-0.01) -> 41.99 | D51: =C51/12/(1+Assumptions!$B$7)*(1-Assumptions!$B$21)-'AI worst case'!$G$33-Assumptions!$B$36 -> -0.68370771 | E51: =(C51-(C51*(Assumptions!$B$22+Assumptions!$B$24)+Assumptions!$B$23))/12-'AI worst case'!$G$33-Assumptions!$B$36 -> 0.25955167 | F51: =IF(D51>='AI worst case'!$B$10,"yes","NO") -> NO | G51: =IF(E51>='AI worst case'!$B$10,"yes","NO") -> yes
A52: In-app a deep founder discount loses money on a learner who maxes every AI allowance; on the web, VAT-exempt, it holds. Sell the founder offer on the landing page (Stripe), or keep the in-app discount small.
A53: Founder rules to write down: who qualifies (early-access sign-ups before a date), until when it can be taken, first year only, then the regular annual price with a reminder 30 days before renewal.

Sheet Credit shop
A1: Credit shop: packs priced so that the subscriptions stay the better deal
A2: Blue = input · prices VAT included · every reward is fixed: nothing random is ever sold or paid for with bought credits (Belgium treats paid loot boxes as gambling).
A4: The credit economy (owner's decisions, Oct 2026; figures to tune with early-access data)
A5: Free: credits refilled a day | B5: 60
A6: Free: refill limit (the refill stops there; earned and bought credits go above it) | B6: 90
A7: Pro: credits refilled a day | B7: 120
A8: Pro: refill limit | B8: 200
A9: Due review on Free (credits) | B9: 1
A10: Due review on Pro and Max (credits) | B10: 0
A11: Practice exercise (2 to 5 by mode; average) | B11: 3
A12: Due reviews a day of a steady Pro learner (for the comparison below) | B12: 60
A14: Packs: the bigger the pack, the bigger the bonus
A15: Pack | B15: Credits | C15: Price (€) | D15: € per 100 credits | E15: Bonus vs the smallest pack | F15: Share of packs sold | G15: You keep in-app (€) | H15: You keep on the web, VAT-exempt (€)
A16: S | B16: 100 | C16: 0.99 | D16: =IF(B16=0,0,C16/B16*100) -> 0.99 | E16: =IF(C16=0,0,B16/(C16/$C$16*$B$16)-1) -> 0 | F16: 0.35 | G16: =C16/(1+Assumptions!$B$7)*(1-Assumptions!$B$21) -> 0.69545455 | H16: =C16-(C16*(Assumptions!$B$22+Assumptions!$B$24)+Assumptions!$B$23) -> 0.71822
A17: M | B17: 330 | C17: 2.99 | D17: =IF(B17=0,0,C17/B17*100) -> 0.90606061 | E17: =IF(C17=0,0,B17/(C17/$C$16*$B$16)-1) -> 0.09264214 | F17: 0.35 | G17: =C17/(1+Assumptions!$B$7)*(1-Assumptions!$B$21) -> 2.1004132 | H17: =C17-(C17*(Assumptions!$B$22+Assumptions!$B$24)+Assumptions!$B$23) -> 2.67422
A18: L | B18: 600 | C18: 4.99 | D18: =IF(B18=0,0,C18/B18*100) -> 0.83166667 | E18: =IF(C18=0,0,B18/(C18/$C$16*$B$16)-1) -> 0.19038076 | F18: 0.2 | G18: =C18/(1+Assumptions!$B$7)*(1-Assumptions!$B$21) -> 3.5053719 | H18: =C18-(C18*(Assumptions!$B$22+Assumptions!$B$24)+Assumptions!$B$23) -> 4.63022
A19: XL | B19: 1300 | C19: 9.99 | D19: =IF(B19=0,0,C19/B19*100) -> 0.76846154 | E19: =IF(C19=0,0,B19/(C19/$C$16*$B$16)-1) -> 0.28828829 | F19: 0.1 | G19: =C19/(1+Assumptions!$B$7)*(1-Assumptions!$B$21) -> 7.0177686 | H19: =C19-(C19*(Assumptions!$B$22+Assumptions!$B$24)+Assumptions!$B$23) -> 9.52022
A20: Mix check (must be 100%) | F20: =SUM(F16:F19) -> 1
A21: Average pack sold | C21: =SUMPRODUCT(C16:C19,F16:F19) -> 3.39 | G21: =SUMPRODUCT(G16:G19,F16:F19) -> 2.381405 | H21: =SUMPRODUCT(H16:H19,F16:F19) -> 3.06542
A22: Kept per pack sold, blended by channel (€) | G22: =Assumptions!$B$58*G21+(1-Assumptions!$B$58)*H21 -> 2.4498065
A24: Do the subscriptions stay the better deal?
A25: Extra credits a month Pro refills over Free | B25: =(B7-B5)*30 -> 1800
A26: Due reviews a month Pro rides free (credits Free would pay) | B26: =B12*30*(B9-B10) -> 1800
A27: A Pro month, in credits | B27: =B25+B26 -> 3600
A28: Those credits bought in packs, at the best rate (€) | B28: =B27*MIN(D16:D19)/100 -> 27.664615
A29: … as a multiple of Pro monthly | B29: =IF(Assumptions!$B$10=0,0,B28/Assumptions!$B$10) -> 5.5440111
A30: Largest limited-time promotion (extra credits on a pack) | B30: 0.5
A31: … multiple of Pro monthly during that promotion | B31: =IF(Assumptions!$B$10=0,0,B28/(1+B30)/Assumptions!$B$10) -> 3.6960074
A32: Target: packs cost at least this multiple of Pro monthly | B32: 1.5
A33: Pro stays the better deal, even during a promotion? | B33: =IF(MIN(B29,B31)>=B32,"yes","NO: raise the pack prices or shrink the bonus") -> yes
A35: Bigger packs carry a bigger bonus (owner's decision). A limited-time promotion adds credits to a pack; it never takes a price off the store's price points.
A36: Show the € price beside every credit amount and every price in credits, never pressure a buy (no fake countdown), and size the packs so nobody is left with an unusable remainder: the EU consumer authorities' principles on in-game virtual currencies (March 2025).
A37: Bought and earned credits never expire (owner's decision) and survive a change of plan. They never raise a plan's AI caps. The shop is hidden from Max (unlimited).

Sheet AI worst case
A1: AI worst case: a user who uses every AI allowance to the full, every day
A2: Caps at the full price (tier 1); cheaper tiers scale them by their multiplier ('Pricing'). Each plan has per-feature caps AND one global ceiling a day, whatever the mix: the worst case is the lower of the two. Only this sheet decides whether a price can lose money.
A4: Model prices (Gemini 3.1 Flash-Lite, the primary)
A5: Input price | B5: 0.25 | C5: $ per 1M tokens | D5: docs/llm-commercial-plan.md. No batch discount in the worst case.
A6: Output price | B6: 1.5 | C6: $ per 1M tokens
A7: Share of input served from the provider's cache | B7: 0.6 | C7: %
A8: Cached input billed at | B8: 0.1 | C8: of the full price
A9: Days in a month | B9: 30 | C9: days
A10: Minimum margin per subscriber per month, worst case | B10: 0.1 | C10: € | D10: 0 = break even; a little above leaves room for error.
A12: Feature (one unit) | B12: Calls per unit | C12: Input tokens per call | D12: Output tokens per call | E12: Cost per unit ($) | F12: Cap per | G12: Free cap | H12: Pro cap | I12: Max cap | J12: Units a month per cap | K12: Free ($/month) | L12: Pro ($/month) | M12: Max ($/month) | N12: What the code does today
A13: New mock-exam paper generated | B13: 35 | C13: 1300 | D13: 2000 | E13: =B13*(C13*$B$5*(1-$B$7+$B$7*$B$8)+D13*$B$6)/1000000 -> 0.1102325 | F13: month | G13: 0 | H13: 2 | I13: 4 | J13: =IF(F13="day",$B$9,1) -> 1 | K13: =G13*$E13*$J13 -> 0 | L13: =H13*$E13*$J13 -> 0.220465 | M13: =I13*$E13*$J13 -> 0.44093 | N13: Papers already in the pool stay open to all (credits). TODAY: 5 new papers a day (EXAM_PAPERS_DAILY_LIMIT).
A14: New comprehension text generated | B14: 1.3 | C14: 2700 | D14: 3000 | E14: =B14*(C14*$B$5*(1-$B$7+$B$7*$B$8)+D14*$B$6)/1000000 -> 0.00625365 | F14: day | G14: 0 | H14: 1 | I14: 2 | J14: =IF(F14="day",$B$9,1) -> 30 | K14: =G14*$E14*$J14 -> 0 | L14: =H14*$E14*$J14 -> 0.1876095 | M14: =I14*$E14*$J14 -> 0.375219 | N14: Texts from the pool are free to serve (30–60 hand-written seeds a level). TODAY: 10 a day (COMPREHENSION_DAILY_LIMIT).
A15: Composition review (one sentence) | B15: 1 | C15: 900 | D15: 400 | E15: =B15*(C15*$B$5*(1-$B$7+$B$7*$B$8)+D15*$B$6)/1000000 -> 0.0007035 | F15: day | G15: 3 | H15: 15 | I15: 25 | J15: =IF(F15="day",$B$9,1) -> 30 | K15: =G15*$E15*$J15 -> 0.063315 | L15: =H15*$E15*$J15 -> 0.316575 | M15: =I15*$E15*$J15 -> 0.527625 | N15: TODAY: 30 a day (COMPOSITION_DAILY_LIMIT).
A16: Translation review (one sentence) | B16: 1 | C16: 600 | D16: 400 | E16: =B16*(C16*$B$5*(1-$B$7+$B$7*$B$8)+D16*$B$6)/1000000 -> 0.000669 | F16: day | G16: 3 | H16: 15 | I16: 25 | J16: =IF(F16="day",$B$9,1) -> 30 | K16: =G16*$E16*$J16 -> 0.06021 | L16: =H16*$E16*$J16 -> 0.30105 | M16: =I16*$E16*$J16 -> 0.50175 | N16: TODAY: 60 a day (TRANSLATION_DAILY_LIMIT).
A17: Conversation: one line spoken (会話) | B17: 1 | C17: 1700 | D17: 450 | E17: =B17*(C17*$B$5*(1-$B$7+$B$7*$B$8)+D17*$B$6)/1000000 -> 0.0008705 | F17: day | G17: 6 | H17: 18 | I17: 30 | J17: =IF(F17="day",$B$9,1) -> 30 | K17: =G17*$E17*$J17 -> 0.15669 | L17: =H17*$E17*$J17 -> 0.47007 | M17: =I17*$E17*$J17 -> 0.78345 | N17: One call answers and reviews the line. TODAY: 80 a day (CONVERSATION_DAILY_LIMIT).
A18: Conversation: translated reply reviewed | B18: 1 | C18: 1100 | D18: 400 | E18: =B18*(C18*$B$5*(1-$B$7+$B$7*$B$8)+D18*$B$6)/1000000 -> 0.0007265 | F18: day | G18: 2 | H18: 8 | I18: 15 | J18: =IF(F18="day",$B$9,1) -> 30 | K18: =G18*$E18*$J18 -> 0.04359 | L18: =H18*$E18*$J18 -> 0.17436 | M18: =I18*$E18*$J18 -> 0.326925 | N18: TODAY: 60 a day (CONVERSATION_REVIEW_DAILY_LIMIT).
A19: Chatbot question (問) | B19: 1 | C19: 1400 | D19: 120 | E19: =B19*(C19*$B$5*(1-$B$7+$B$7*$B$8)+D19*$B$6)/1000000 -> 0.000341 | F19: day | G19: 5 | H19: 20 | I19: 40 | J19: =IF(F19="day",$B$9,1) -> 30 | K19: =G19*$E19*$J19 -> 0.05115 | L19: =H19*$E19*$J19 -> 0.2046 | M19: =I19*$E19*$J19 -> 0.4092 | N19: TODAY: 40 a day (ASK_DAILY_LIMIT).
A20: Explain / analyser (a sentence not in the cache) | B20: 1 | C20: 400 | D20: 500 | E20: =B20*(C20*$B$5*(1-$B$7+$B$7*$B$8)+D20*$B$6)/1000000 -> 0.000796 | F20: day | G20: 5 | H20: 15 | I20: 30 | J20: =IF(F20="day",$B$9,1) -> 30 | K20: =G20*$E20*$J20 -> 0.1194 | L20: =H20*$E20*$J20 -> 0.3582 | M20: =I20*$E20*$J20 -> 0.7164 | N20: Cached sentences stay unlimited. TODAY: 150 a day (DEEP_DAILY_LIMIT).
A21: Photo reading (OCR) | B21: 1 | C21: 1400 | D21: 400 | E21: =B21*(C21*$B$5*(1-$B$7+$B$7*$B$8)+D21*$B$6)/1000000 -> 0.000761 | F21: day | G21: 1 | H21: 5 | I21: 15 | J21: =IF(F21="day",$B$9,1) -> 30 | K21: =G21*$E21*$J21 -> 0.02283 | L21: =H21*$E21*$J21 -> 0.11415 | M21: =I21*$E21*$J21 -> 0.34245 | N21: TODAY: 20 a day (OCR_DAILY_LIMIT).
A22: Video / passage: a block of 20 lines translated | B22: 1 | C22: 900 | D22: 700 | E22: =B22*(C22*$B$5*(1-$B$7+$B$7*$B$8)+D22*$B$6)/1000000 -> 0.0011535 | F22: day | G22: 2 | H22: 8 | I22: 20 | J22: =IF(F22="day",$B$9,1) -> 30 | K22: =G22*$E22*$J22 -> 0.06921 | L22: =H22*$E22*$J22 -> 0.27684 | M22: =I22*$E22*$J22 -> 0.6921 | N22: A video of ~150 lines is ~8 blocks. TODAY: 60 a day (LINE_TRANSLATION_DAILY_LIMIT).
A23: Song lyrics sorted | B23: 1 | C23: 1400 | D23: 900 | E23: =B23*(C23*$B$5*(1-$B$7+$B$7*$B$8)+D23*$B$6)/1000000 -> 0.001511 | F23: day | G23: 0 | H23: 2 | I23: 5 | J23: =IF(F23="day",$B$9,1) -> 30 | K23: =G23*$E23*$J23 -> 0 | L23: =H23*$E23*$J23 -> 0.09066 | M23: =I23*$E23*$J23 -> 0.22665 | N23: TODAY: 20 a day (LYRICS_SORT_DAILY_LIMIT).
A24: Sum of the per-feature caps ($/month) | K24: =SUM(K13:K23) -> 0.586395 | L24: =SUM(L13:L23) -> 2.7145795 | M24: =SUM(M13:M23) -> 5.342699
A25: Global AI ceiling a day, whatever the mix ($) | G25: 0.01 | H25: 0.08 | I25: 0.1 | K25: =G25*$B$9 -> 0.3 | L25: =H25*$B$9 -> 2.4 | M25: =I25*$B$9 -> 3 | N25: Proposal. Counted in $ of model cost a learner causes in a day, from the usage log: it never shows, it only stops an abuser.
A26: Worst case per month, full price ($) | K26: =MIN(K24,K25) -> 0.3 | L26: =MIN(L24,L25) -> 2.4 | M26: =MIN(M24,M25) -> 3
A27: … in €, with the non-deductible VAT on services bought abroad | K27: =K26*Assumptions!$B$6*(1+Assumptions!$B$8) -> 0.31218 | L27: =L26*Assumptions!$B$6*(1+Assumptions!$B$8) -> 2.49744 | M27: =M26*Assumptions!$B$6*(1+Assumptions!$B$8) -> 3.1218
A28: The ceiling, as composition reviews in one day | G28: =IF($E$15=0,0,G25/$E$15) -> 14.214641 | H28: =IF($E$15=0,0,H25/$E$15) -> 113.71713 | I28: =IF($E$15=0,0,I25/$E$15) -> 142.14641
A29: The ceiling, as chatbot questions in one day | G29: =IF($E$19=0,0,G25/$E$19) -> 29.325513 | H29: =IF($E$19=0,0,H25/$E$19) -> 234.60411 | I29: =IF($E$19=0,0,I25/$E$19) -> 293.25513
A31: By regional tier (caps and ceiling scaled by the tier's multiplier)
A32: Tier | B32: Pro multiplier | C32: Max multiplier | D32: Pro worst case ($/mo) | E32: Max worst case ($/mo) | F32: Pro worst case (€/mo) | G32: Max worst case (€/mo)
A33: =Pricing!A35 -> 1 – Full price | B33: =Pricing!D35 -> 1 | C33: =Pricing!E35 -> 1 | D33: =MIN(SUMPRODUCT(ROUNDDOWN($H$13:$H$23*B33,0),$E$13:$E$23,$J$13:$J$23),$H$25*B33*$B$9) -> 2.4 | E33: =MIN(SUMPRODUCT(ROUNDDOWN($I$13:$I$23*C33,0),$E$13:$E$23,$J$13:$J$23),$I$25*C33*$B$9) -> 3 | F33: =D33*Assumptions!$B$6*(1+Assumptions!$B$8) -> 2.49744 | G33: =E33*Assumptions!$B$6*(1+Assumptions!$B$8) -> 3.1218
A34: =Pricing!A36 -> 2 – Reduced | B34: =Pricing!D36 -> 0.75 | C34: =Pricing!E36 -> 0.75 | D34: =MIN(SUMPRODUCT(ROUNDDOWN($H$13:$H$23*B34,0),$E$13:$E$23,$J$13:$J$23),$H$25*B34*$B$9) -> 1.7710025 | E34: =MIN(SUMPRODUCT(ROUNDDOWN($I$13:$I$23*C34,0),$E$13:$E$23,$J$13:$J$23),$I$25*C34*$B$9) -> 2.25 | F34: =D34*Assumptions!$B$6*(1+Assumptions!$B$8) -> 1.8429052 | G34: =E34*Assumptions!$B$6*(1+Assumptions!$B$8) -> 2.34135
A35: =Pricing!A37 -> 3 – Low | B35: =Pricing!D37 -> 0.55 | C35: =Pricing!E37 -> 0.55 | D35: =MIN(SUMPRODUCT(ROUNDDOWN($H$13:$H$23*B35,0),$E$13:$E$23,$J$13:$J$23),$H$25*B35*$B$9) -> 1.2948275 | E35: =MIN(SUMPRODUCT(ROUNDDOWN($I$13:$I$23*C35,0),$E$13:$E$23,$J$13:$J$23),$I$25*C35*$B$9) -> 1.65 | F35: =D35*Assumptions!$B$6*(1+Assumptions!$B$8) -> 1.3473975 | G35: =E35*Assumptions!$B$6*(1+Assumptions!$B$8) -> 1.71699
A36: =Pricing!A38 -> 4 – Lowest | B36: =Pricing!D38 -> 0.45 | C36: =Pricing!E38 -> 0.45 | D36: =MIN(SUMPRODUCT(ROUNDDOWN($H$13:$H$23*B36,0),$E$13:$E$23,$J$13:$J$23),$H$25*B36*$B$9) -> 0.90618 | E36: =MIN(SUMPRODUCT(ROUNDDOWN($I$13:$I$23*C36,0),$E$13:$E$23,$J$13:$J$23),$I$25*C36*$B$9) -> 1.35 | F36: =D36*Assumptions!$B$6*(1+Assumptions!$B$8) -> 0.94297091 | G36: =E36*Assumptions!$B$6*(1+Assumptions!$B$8) -> 1.40481
A38: Expected use is far below this (Assumptions: ≈ $0.27 Pro, $0.44 Max, $0.02 Free). This sheet is a floor for prices, not a forecast.
A39: Credits bought in packs never raise a plan's AI caps: a Free learner who buys credits keeps Free's caps. PvP scores, corrections and the solo games are assumed to call no model (pre-generated content).

Sheet Start-up costs
A1: One-off costs to start
A2: Include = Y counts in the totals · amounts in the currency named · the € columns are calculated, adding the non-deductible VAT on services bought abroad (Assumptions).
A4: Item | B4: Category | C4: Include (Y/N) | D4: Currency | E4: Low | F4: Expected | G4: High | H4: Low (€) | I4: Expected (€) | J4: High (€) | K4: Note / source
A5: Registration in the BCE (enterprise number) via a guichet d'entreprises | B5: Legal & admin | C5: Y | D5: EUR | E5: 111.5 | F5: 111.5 | G5: 111.5 | H5: =E5*IF($D5="USD",Assumptions!$B$6*(1+Assumptions!$B$8),1) -> 111.5 | I5: =F5*IF($D5="USD",Assumptions!$B$6*(1+Assumptions!$B$8),1) -> 111.5 | J5: =G5*IF($D5="USD",Assumptions!$B$6*(1+Assumptions!$B$8),1) -> 111.5 | K5: 2026 official fee, the same at every guichet. VAT activation through the guichet is included. Ask for the small-business VAT exemption (franchise) at the same time.
A6: Student self-employed status (étudiant-indépendant) | B6: Legal & admin | C6: Y | D6: EUR | E6: 0 | F6: 0 | G6: 0 | H6: =E6*IF($D6="USD",Assumptions!$B$6*(1+Assumptions!$B$8),1) -> 0 | I6: =F6*IF($D6="USD",Assumptions!$B$6*(1+Assumptions!$B$8),1) -> 0 | J6: =G6*IF($D6="USD",Assumptions!$B$6*(1+Assumptions!$B$8),1) -> 0 | K6: Free: request it from your social insurance fund, with proof of enrolment every academic year (18–25 years old, at least 27 credits).
A7: VAT number activation | B7: Legal & admin | C7: Y | D7: EUR | E7: 0 | F7: 0 | G7: 0 | H7: =E7*IF($D7="USD",Assumptions!$B$6*(1+Assumptions!$B$8),1) -> 0 | I7: =F7*IF($D7="USD",Assumptions!$B$6*(1+Assumptions!$B$8),1) -> 0 | J7: =G7*IF($D7="USD",Assumptions!$B$6*(1+Assumptions!$B$8),1) -> 0 | K7: Included in the BCE fee. Under the exemption you file no periodic VAT returns, only the special return for services bought abroad.
A8: Joining a social insurance fund (caisse d'assurances sociales) | B8: Legal & admin | C8: Y | D8: EUR | E8: 0 | F8: 0 | G8: 0 | H8: =E8*IF($D8="USD",Assumptions!$B$6*(1+Assumptions!$B$8),1) -> 0 | I8: =F8*IF($D8="USD",Assumptions!$B$6*(1+Assumptions!$B$8),1) -> 0 | J8: =G8*IF($D8="USD",Assumptions!$B$6*(1+Assumptions!$B$8),1) -> 0 | K8: Free to join. The contributions are in 'Assumptions' and 'Projection'.
A9: Setting up a company (SRL) instead of working in your own name | B9: Legal & admin | C9: N | D9: EUR | E9: 1000 | F9: 1400 | G9: 2000 | H9: =E9*IF($D9="USD",Assumptions!$B$6*(1+Assumptions!$B$8),1) -> 1000 | I9: =F9*IF($D9="USD",Assumptions!$B$6*(1+Assumptions!$B$8),1) -> 1400 | J9: =G9*IF($D9="USD",Assumptions!$B$6*(1+Assumptions!$B$8),1) -> 2000 | K9: Not compatible with the student self-employed status as a sole trader. Only for later, once profit passes the student limit.
A10: Benelux trademark 'Tsuji' (BOIP), classes 9 (software) + 41 (education) | B10: Legal & admin | C10: Y | D10: EUR | E10: 271 | F10: 271 | G10: 271 | H10: =E10*IF($D10="USD",Assumptions!$B$6*(1+Assumptions!$B$8),1) -> 271 | I10: =F10*IF($D10="USD",Assumptions!$B$6*(1+Assumptions!$B$8),1) -> 271 | J10: =G10*IF($D10="USD",Assumptions!$B$6*(1+Assumptions!$B$8),1) -> 271 | K10: BOIP: €244 for the first class, €27 for each extra class. Valid 10 years. Check the fee on boip.int before filing.
A11: EU trademark (EUIPO), classes 9 + 41 | B11: Legal & admin | C11: N | D11: EUR | E11: 900 | F11: 900 | G11: 900 | H11: =E11*IF($D11="USD",Assumptions!$B$6*(1+Assumptions!$B$8),1) -> 900 | I11: =F11*IF($D11="USD",Assumptions!$B$6*(1+Assumptions!$B$8),1) -> 900 | J11: =G11*IF($D11="USD",Assumptions!$B$6*(1+Assumptions!$B$8),1) -> 900 | K11: €850 + €50 for the second class. Covers the whole EU instead of Benelux only.
A12: Trademark clearance search / IP attorney | B12: Legal & admin | C12: N | D12: EUR | E12: 0 | F12: 0 | G12: 500 | H12: =E12*IF($D12="USD",Assumptions!$B$6*(1+Assumptions!$B$8),1) -> 0 | I12: =F12*IF($D12="USD",Assumptions!$B$6*(1+Assumptions!$B$8),1) -> 0 | J12: =G12*IF($D12="USD",Assumptions!$B$6*(1+Assumptions!$B$8),1) -> 500 | K12: 'Tsuji' is a common Japanese surname. Check nobody already holds it in classes 9/41.
A13: Legal texts: terms of use, terms of sale, subscription and withdrawal terms | B13: Legal & admin | C13: Y | D13: EUR | E13: 0 | F13: 400 | G13: 1500 | H13: =E13*IF($D13="USD",Assumptions!$B$6*(1+Assumptions!$B$8),1) -> 0 | I13: =F13*IF($D13="USD",Assumptions!$B$6*(1+Assumptions!$B$8),1) -> 400 | J13: =G13*IF($D13="USD",Assumptions!$B$6*(1+Assumptions!$B$8),1) -> 1500 | K13: EU consumer law: the 14-day withdrawal right, auto-renewal terms. public/privacy.html already exists.
A14: Accountant onboarding | B14: Legal & admin | C14: Y | D14: EUR | E14: 0 | F14: 150 | G14: 300 | H14: =E14*IF($D14="USD",Assumptions!$B$6*(1+Assumptions!$B$8),1) -> 0 | I14: =F14*IF($D14="USD",Assumptions!$B$6*(1+Assumptions!$B$8),1) -> 150 | J14: =G14*IF($D14="USD",Assumptions!$B$6*(1+Assumptions!$B$8),1) -> 300 | K14: Some offices charge a set-up fee.
A15: Google Play developer registration | B15: Stores & tech | C15: Y | D15: USD | E15: 25 | F15: 25 | G15: 25 | H15: =E15*IF($D15="USD",Assumptions!$B$6*(1+Assumptions!$B$8),1) -> 26.015 | I15: =F15*IF($D15="USD",Assumptions!$B$6*(1+Assumptions!$B$8),1) -> 26.015 | J15: =G15*IF($D15="USD",Assumptions!$B$6*(1+Assumptions!$B$8),1) -> 26.015 | K15: Paid once. (The Apple fee is yearly, so it is in 'Fixed costs'.)
A16: Mac for building and uploading the iOS app | B16: Stores & tech | C16: N | D16: EUR | E16: 0 | F16: 0 | G16: 700 | H16: =E16*IF($D16="USD",Assumptions!$B$6*(1+Assumptions!$B$8),1) -> 0 | I16: =F16*IF($D16="USD",Assumptions!$B$6*(1+Assumptions!$B$8),1) -> 0 | J16: =G16*IF($D16="USD",Assumptions!$B$6*(1+Assumptions!$B$8),1) -> 700 | K16: Only if you don't own one. Cloud macOS build services are the alternative.
A17: Test devices (a used iPhone and Android phone) | B17: Stores & tech | C17: N | D17: EUR | E17: 0 | F17: 150 | G17: 400 | H17: =E17*IF($D17="USD",Assumptions!$B$6*(1+Assumptions!$B$8),1) -> 0 | I17: =F17*IF($D17="USD",Assumptions!$B$6*(1+Assumptions!$B$8),1) -> 150 | J17: =G17*IF($D17="USD",Assumptions!$B$6*(1+Assumptions!$B$8),1) -> 400
A18: First fill of the LLM pools (exam papers, comprehension, phrase cache) | B18: Stores & tech | C18: Y | D18: USD | E18: 10 | F18: 20 | G18: 40 | H18: =E18*IF($D18="USD",Assumptions!$B$6*(1+Assumptions!$B$8),1) -> 10.406 | I18: =F18*IF($D18="USD",Assumptions!$B$6*(1+Assumptions!$B$8),1) -> 20.812 | J18: =G18*IF($D18="USD",Assumptions!$B$6*(1+Assumptions!$B$8),1) -> 41.624 | K18: 10 papers for each of the 15 exam ids ≈ $17 (≈ $0.11 a paper), comprehension pool ≈ $2, phrase cache ≈ $0.20. A deep paper pool means the new-paper allowance is almost never reached.
A19: Payment integration (Stripe / RevenueCat) | B19: Stores & tech | C19: Y | D19: EUR | E19: 0 | F19: 0 | G19: 0 | H19: =E19*IF($D19="USD",Assumptions!$B$6*(1+Assumptions!$B$8),1) -> 0 | I19: =F19*IF($D19="USD",Assumptions!$B$6*(1+Assumptions!$B$8),1) -> 0 | J19: =G19*IF($D19="USD",Assumptions!$B$6*(1+Assumptions!$B$8),1) -> 0 | K19: No set-up fee. The work is development time (HAS_STORE is still false).
A20: Voice licences (VOICEVOX Nemo, kana voice) | B20: Stores & tech | C20: Y | D20: EUR | E20: 0 | F20: 0 | G20: 0 | H20: =E20*IF($D20="USD",Assumptions!$B$6*(1+Assumptions!$B$8),1) -> 0 | I20: =F20*IF($D20="USD",Assumptions!$B$6*(1+Assumptions!$B$8),1) -> 0 | J20: =G20*IF($D20="USD",Assumptions!$B$6*(1+Assumptions!$B$8),1) -> 0 | K20: Free, but you must credit 'VOICEVOX Nemo' (already done), and generated audio must never be used for machine learning.
A21: Launch marketing (ads, store screenshots, video) | B21: Marketing | C21: N | D21: EUR | E21: 0 | F21: 300 | G21: 1500 | H21: =E21*IF($D21="USD",Assumptions!$B$6*(1+Assumptions!$B$8),1) -> 0 | I21: =F21*IF($D21="USD",Assumptions!$B$6*(1+Assumptions!$B$8),1) -> 300 | J21: =G21*IF($D21="USD",Assumptions!$B$6*(1+Assumptions!$B$8),1) -> 1500 | K21: Optional. The landing page and its footage are self-made.
A23: Total – included items (Y) | H23: =SUMIFS(H5:H21,$C$5:$C$21,"Y") -> 418.921 | I23: =SUMIFS(I5:I21,$C$5:$C$21,"Y") -> 979.327 | J23: =SUMIFS(J5:J21,$C$5:$C$21,"Y") -> 2250.139
A24: Total – every item, including optional | H24: =SUM(H5:H21) -> 2318.921 | I24: =SUM(I5:I21) -> 3729.327 | J24: =SUM(J5:J21) -> 8250.139

Sheet Fixed costs
A1: Recurring fixed costs, by stage
A2: Amounts as billed (currency and period named) · € per month is calculated, adding the non-deductible VAT on services bought abroad · Include = Y counts in the totals.
A4: Item | B4: Category | C4: Include (Y/N) | D4: Currency | E4: Billed per | F4: Launch | G4: Growth | H4: Scale | I4: Launch (€/mo) | J4: Growth (€/mo) | K4: Scale (€/mo) | L4: Note / source
A5: Render – backend (FastAPI web service) | B5: Hosting | C5: Y | D5: USD | E5: month | F5: 7 | G5: 25 | H5: 85 | I5: =F5*IF($D5="USD",Assumptions!$B$6*(1+Assumptions!$B$8),1)/IF($E5="year",12,1) -> 7.2842 | J5: =G5*IF($D5="USD",Assumptions!$B$6*(1+Assumptions!$B$8),1)/IF($E5="year",12,1) -> 26.015 | K5: =H5*IF($D5="USD",Assumptions!$B$6*(1+Assumptions!$B$8),1)/IF($E5="year",12,1) -> 88.451 | L5: render.yaml: plan 'starter' (512 MB, 0.5 CPU). Standard $25 (2 GB, 1 CPU), Pro $85 (4 GB, 2 CPU).
A6: Render – persistent disk (exam and dictation audio) | B6: Hosting | C6: Y | D6: USD | E6: month | F6: 0.25 | G6: 1.25 | H6: 5 | I6: =F6*IF($D6="USD",Assumptions!$B$6*(1+Assumptions!$B$8),1)/IF($E6="year",12,1) -> 0.26015 | J6: =G6*IF($D6="USD",Assumptions!$B$6*(1+Assumptions!$B$8),1)/IF($E6="year",12,1) -> 1.30075 | K6: =H6*IF($D6="USD",Assumptions!$B$6*(1+Assumptions!$B$8),1)/IF($E6="year",12,1) -> 5.203 | L6: $0.25 per GB per month. render.yaml: 1 GB → 5 GB → 20 GB.
A7: Render – VOICEVOX Nemo voice engine (private service) | B7: Hosting | C7: Y | D7: USD | E7: month | F7: 7 | G7: 25 | H7: 25 | I7: =F7*IF($D7="USD",Assumptions!$B$6*(1+Assumptions!$B$8),1)/IF($E7="year",12,1) -> 7.2842 | J7: =G7*IF($D7="USD",Assumptions!$B$6*(1+Assumptions!$B$8),1)/IF($E7="year",12,1) -> 26.015 | K7: =H7*IF($D7="USD",Assumptions!$B$6*(1+Assumptions!$B$8),1)/IF($E7="year",12,1) -> 26.015 | L7: ADR 0019: Starter holds it (343 MB) but slowly; Standard halves the first-play wait.
A8: Render – workspace plan | B8: Hosting | C8: Y | D8: USD | E8: month | F8: 0 | G8: 0 | H8: 19 | I8: =F8*IF($D8="USD",Assumptions!$B$6*(1+Assumptions!$B$8),1)/IF($E8="year",12,1) -> 0 | J8: =G8*IF($D8="USD",Assumptions!$B$6*(1+Assumptions!$B$8),1)/IF($E8="year",12,1) -> 0 | K8: =H8*IF($D8="USD",Assumptions!$B$6*(1+Assumptions!$B$8),1)/IF($E8="year",12,1) -> 19.7714 | L8: Hobby is free. Professional ($19 per member) for autoscaling and a second instance.
A9: Vercel – frontend and /api proxy | B9: Hosting | C9: Y | D9: USD | E9: month | F9: 20 | G9: 20 | H9: 20 | I9: =F9*IF($D9="USD",Assumptions!$B$6*(1+Assumptions!$B$8),1)/IF($E9="year",12,1) -> 20.812 | J9: =G9*IF($D9="USD",Assumptions!$B$6*(1+Assumptions!$B$8),1)/IF($E9="year",12,1) -> 20.812 | K9: =H9*IF($D9="USD",Assumptions!$B$6*(1+Assumptions!$B$8),1)/IF($E9="year",12,1) -> 20.812 | L9: The free Hobby plan is non-commercial only. A paid app needs Pro ($20 per member; 1 TB of traffic included).
A10: Supabase – Postgres database + authentication | B10: Hosting | C10: Y | D10: USD | E10: month | F10: 25 | G10: 30 | H10: 75 | I10: =F10*IF($D10="USD",Assumptions!$B$6*(1+Assumptions!$B$8),1)/IF($E10="year",12,1) -> 26.015 | J10: =G10*IF($D10="USD",Assumptions!$B$6*(1+Assumptions!$B$8),1)/IF($E10="year",12,1) -> 31.218 | K10: =H10*IF($D10="USD",Assumptions!$B$6*(1+Assumptions!$B$8),1)/IF($E10="year",12,1) -> 78.045 | L10: The free plan pauses after 7 idle days and has no backups. Pro $25 includes 100k MAU, 8 GB of disk and Micro compute; Small compute +$5, Medium +$50.
A11: Transactional e-mail for auth (sign-up confirmation, password reset) | B11: Hosting | C11: Y | D11: USD | E11: month | F11: 0 | G11: 20 | H11: 20 | I11: =F11*IF($D11="USD",Assumptions!$B$6*(1+Assumptions!$B$8),1)/IF($E11="year",12,1) -> 0 | J11: =G11*IF($D11="USD",Assumptions!$B$6*(1+Assumptions!$B$8),1)/IF($E11="year",12,1) -> 20.812 | K11: =H11*IF($D11="USD",Assumptions!$B$6*(1+Assumptions!$B$8),1)/IF($E11="year",12,1) -> 20.812 | L11: Supabase's built-in mail is for testing only (a few mails an hour). E.g. Resend: free for 3,000 a month (100 a day), $20 for 50,000.
A12: Error tracking and uptime monitoring | B12: Hosting | C12: Y | D12: USD | E12: month | F12: 0 | G12: 0 | H12: 26 | I12: =F12*IF($D12="USD",Assumptions!$B$6*(1+Assumptions!$B$8),1)/IF($E12="year",12,1) -> 0 | J12: =G12*IF($D12="USD",Assumptions!$B$6*(1+Assumptions!$B$8),1)/IF($E12="year",12,1) -> 0 | K12: =H12*IF($D12="USD",Assumptions!$B$6*(1+Assumptions!$B$8),1)/IF($E12="year",12,1) -> 27.0556 | L12: Free plans are enough early. Sentry Team $26.
A13: LLM – offline jobs (refilling the comprehension pool, new exam papers) | B13: AI | C13: Y | D13: USD | E13: month | F13: 2 | G13: 5 | H13: 10 | I13: =F13*IF($D13="USD",Assumptions!$B$6*(1+Assumptions!$B$8),1)/IF($E13="year",12,1) -> 2.0812 | J13: =G13*IF($D13="USD",Assumptions!$B$6*(1+Assumptions!$B$8),1)/IF($E13="year",12,1) -> 5.203 | K13: =H13*IF($D13="USD",Assumptions!$B$6*(1+Assumptions!$B$8),1)/IF($E13="year",12,1) -> 10.406 | L13: Not tied to any one user. §5.4: a full prewarm ≈ $4. Per-user LLM spend is in 'Unit economics'.
A14: Rotating residential proxy (fetching YouTube subtitles) | B14: AI | C14: N | D14: USD | E14: month | F14: 3.5 | G14: 7 | H14: 14 | I14: =F14*IF($D14="USD",Assumptions!$B$6*(1+Assumptions!$B$8),1)/IF($E14="year",12,1) -> 3.6421 | J14: =G14*IF($D14="USD",Assumptions!$B$6*(1+Assumptions!$B$8),1)/IF($E14="year",12,1) -> 7.2842 | K14: =H14*IF($D14="USD",Assumptions!$B$6*(1+Assumptions!$B$8),1)/IF($E14="year",12,1) -> 14.5684 | L14: Only if you switch the YouTube-link feature on (it is off today). Webshare Rotating Residential $3.50 per GB, ≈ 2,500 analyses per GB.
A15: Domain name (e.g. tsuji.app) | B15: Web | C15: Y | D15: USD | E15: year | F15: 15 | G15: 15 | H15: 15 | I15: =F15*IF($D15="USD",Assumptions!$B$6*(1+Assumptions!$B$8),1)/IF($E15="year",12,1) -> 1.30075 | J15: =G15*IF($D15="USD",Assumptions!$B$6*(1+Assumptions!$B$8),1)/IF($E15="year",12,1) -> 1.30075 | K15: =H15*IF($D15="USD",Assumptions!$B$6*(1+Assumptions!$B$8),1)/IF($E15="year",12,1) -> 1.30075 | L15: The app still runs on japanese-learner-seven.vercel.app. A .app domain costs ≈ $14–20 a year.
A16: Contact mailbox (contact@…) | B16: Web | C16: Y | D16: EUR | E16: month | F16: 0 | G16: 0 | H16: 7 | I16: =F16*IF($D16="USD",Assumptions!$B$6*(1+Assumptions!$B$8),1)/IF($E16="year",12,1) -> 0 | J16: =G16*IF($D16="USD",Assumptions!$B$6*(1+Assumptions!$B$8),1)/IF($E16="year",12,1) -> 0 | K16: =H16*IF($D16="USD",Assumptions!$B$6*(1+Assumptions!$B$8),1)/IF($E16="year",12,1) -> 7 | L16: Free forwarding at first (e.g. Cloudflare Email Routing), then a real mailbox.
... A22: Paid acquisition / ads | B22: Marketing | C22: N | D22: EUR | E22: month | F22: 0 | G22: 200 | H22: 1000 | I22: =F22*IF($D22="USD",Assumptions!$B$6*(1+Assumptions!$B$8),1)/IF($E22="year",12,1) -> 0 | J22: =G22*IF($D22="USD",Assumptions!$B$6*(1+Assumptions!$B$8),1)/IF($E22="year",12,1) -> 200 | K22: =H22*IF($D22="USD",Assumptions!$B$6*(1+Assumptions!$B$8),1)/IF($E22="year",12,1) -> 1000 | L22: Optional. Set it once you know your cost per install.
A24: Total per month – included items (Y) | I24: =SUMIFS(I5:I22,$C$5:$C$22,"Y") -> 232.68245 | J24: =SUMIFS(J5:J22,$C$5:$C$22,"Y") -> 355.32145 | K24: =SUMIFS(K5:K22,$C$5:$C$22,"Y") -> 736.5767
A25: Total per year – included items (Y) | I25: =I24*12 -> 2792.1894 | J25: =J24*12 -> 4263.8574 | K25: =K24*12 -> 8838.9204
A26: Total per month – every item, including optional | I26: =SUM(I5:I22) -> 236.32455 | J26: =SUM(J5:J22) -> 587.60565 | K26: =SUM(K5:K22) -> 1791.1451
A28: Stages: Launch below the Growth threshold, Growth from it, Scale from the Scale threshold (see Assumptions).

Sheet Unit economics
A1: Unit economics: what one subscriber brings in and costs, per month
A2: Prices are averaged over the regional tiers (Pricing) · annual plans are spread over 12 months · in-app and web sales are blended by the channel mix · VAT shown as if charged on the web too (the exemption is added back in 'Projection'). · annual plans carry the founder discount for the share of payers in their founder year (Assumptions) · the 7-day trial's cost is spread over the year it buys.
A4: Plan | B4: Billing | C4: Average price paid incl. VAT (€) | D4: Months covered | E4: Charges per month | F4: Gross per month (€) | G4: VAT (€) | H4: Net of VAT (€) | I4: Store commission if sold in-app (€) | J4: Stripe fees if sold on web (€) | K4: Payment cost, blended (€) | L4: Net revenue (€) | M4: LLM, expected (€) | N4: Infrastructure (€) | O4: Contribution margin (€) | P4: Margin % of gross | Q4: LLM, worst case (€) | R4: Margin, worst case (€) | S4: Discount vs monthly
A5: Pro | B5: Monthly | C5: =Assumptions!$B$10*Pricing!$D$39 -> 4.4411 | D5: 1 | E5: =1/D5 -> 1 | F5: =C5/D5 -> 4.4411 | G5: =F5-H5 -> 0.77076942 | H5: =F5/(1+Assumptions!$B$7) -> 3.6703306 | I5: =H5*Assumptions!$B$21 -> 0.55054959 | J5: =F5*(Assumptions!$B$22+Assumptions!$B$24)+Assumptions!$B$23*E5 -> 0.3477042 | K5: =Assumptions!$B$19*I5+(1-Assumptions!$B$19)*J5 -> 0.46941143 | L5: =H5-K5 -> 3.2009191 | M5: =Assumptions!$B$31*Assumptions!$B$6*(1+Assumptions!$B$8) -> 0.280962 | N5: =Assumptions!$B$36 -> 0.02 | O5: =L5-M5-N5 -> 2.8999571 | P5: =IF(F5=0,0,O5/F5) -> 0.65298173 | Q5: =Assumptions!$B$32*Assumptions!$B$6*(1+Assumptions!$B$8) -> 2.49744 | R5: =L5-Q5-N5 -> 0.68347915
A6: Pro | B6: Annual | C6: =Assumptions!$B$11*Pricing!$D$39*(1-Assumptions!$B$53*Assumptions!$B$52) -> 31.14377 | D6: 12 | E6: =1/D6 -> 0.083333333 | F6: =C6/D6 -> 2.5953142 | G6: =F6-H6 -> 0.45042643 | H6: =F6/(1+Assumptions!$B$7) -> 2.1448877 | I6: =H6*Assumptions!$B$21 -> 0.32173316 | J6: =F6*(Assumptions!$B$22+Assumptions!$B$24)+Assumptions!$B$23*E6 -> 0.077930245 | K6: =Assumptions!$B$19*I6+(1-Assumptions!$B$19)*J6 -> 0.22421199 | L6: =H6-K6 -> 1.9206757 | M6: =Assumptions!$B$31*Assumptions!$B$6*(1+Assumptions!$B$8) -> 0.280962 | N6: =Assumptions!$B$36 -> 0.02 | O6: =L6-M6-N6-$C$35 -> 1.6109357 | P6: =IF(F6=0,0,O6/F6) -> 0.62070932 | Q6: =Assumptions!$B$32*Assumptions!$B$6*(1+Assumptions!$B$8) -> 2.49744 | R6: =L6-Q6-N6-$C$35 -> -0.60554231 | S6: =1-C6/(12*C5) -> 0.41561456
A7: Max | B7: Monthly | C7: =Assumptions!$B$12*Pricing!$E$39 -> 7.1111 | D7: 1 | E7: =1/D7 -> 1 | F7: =C7/D7 -> 7.1111 | G7: =F7-H7 -> 1.2341579 | H7: =F7/(1+Assumptions!$B$7) -> 5.8769421 | I7: =H7*Assumptions!$B$21 -> 0.88154132 | J7: =F7*(Assumptions!$B$22+Assumptions!$B$24)+Assumptions!$B$23*E7 -> 0.4064442 | K7: =Assumptions!$B$19*I7+(1-Assumptions!$B$19)*J7 -> 0.69150247 | L7: =H7-K7 -> 5.1854397 | M7: =Assumptions!$B$33*Assumptions!$B$6*(1+Assumptions!$B$8) -> 0.457864 | N7: =Assumptions!$B$36 -> 0.02 | O7: =L7-M7-N7 -> 4.7075757 | P7: =IF(F7=0,0,O7/F7) -> 0.66200386 | Q7: =Assumptions!$B$34*Assumptions!$B$6*(1+Assumptions!$B$8) -> 3.1218 | R7: =L7-Q7-N7 -> 2.0436397
A8: Max | B8: Annual | C8: =Assumptions!$B$13*Pricing!$E$39*(1-Assumptions!$B$53*Assumptions!$B$52) -> 37.37377 | D8: 12 | E8: =1/D8 -> 0.083333333 | F8: =C8/D8 -> 3.1144808 | G8: =F8-H8 -> 0.54052973 | H8: =F8/(1+Assumptions!$B$7) -> 2.5739511 | I8: =H8*Assumptions!$B$21 -> 0.38609267 | J8: =F8*(Assumptions!$B$22+Assumptions!$B$24)+Assumptions!$B$23*E8 -> 0.089351912 | K8: =Assumptions!$B$19*I8+(1-Assumptions!$B$19)*J8 -> 0.26739636 | L8: =H8-K8 -> 2.3065547 | M8: =Assumptions!$B$33*Assumptions!$B$6*(1+Assumptions!$B$8) -> 0.457864 | N8: =Assumptions!$B$36 -> 0.02 | O8: =L8-M8-N8-$C$36 -> 1.814753 | P8: =IF(F8=0,0,O8/F8) -> 0.58268236 | Q8: =Assumptions!$B$34*Assumptions!$B$6*(1+Assumptions!$B$8) -> 3.1218 | R8: =L8-Q8-N8-$C$36 -> -0.84918296 | S8: =1-C8/(12*C7) -> 0.56202545
A10: Blended by each plan's annual share (Assumptions)
A11: Pro | B11: Blended | F11: =(1-Assumptions!$B$17)*F5+Assumptions!$B$17*F6 -> 3.1490499 | G11: =(1-Assumptions!$B$17)*G5+Assumptions!$B$17*G6 -> 0.54652932 | H11: =(1-Assumptions!$B$17)*H5+Assumptions!$B$17*H6 -> 2.6025206 | K11: =(1-Assumptions!$B$17)*K5+Assumptions!$B$17*K6 -> 0.29777183 | L11: =(1-Assumptions!$B$17)*L5+Assumptions!$B$17*L6 -> 2.3047488 | M11: =(1-Assumptions!$B$17)*M5+Assumptions!$B$17*M6 -> 0.280962 | N11: =(1-Assumptions!$B$17)*N5+Assumptions!$B$17*N6 -> 0.02 | O11: =(1-Assumptions!$B$17)*O5+Assumptions!$B$17*O6 -> 1.9976421 | P11: =IF(F11=0,0,O11/F11) -> 0.63436344 | Q11: =(1-Assumptions!$B$17)*Q5+Assumptions!$B$17*Q6 -> 2.49744 | R11: =(1-Assumptions!$B$17)*R5+Assumptions!$B$17*R6 -> -0.21883587
A12: Max | B12: Blended | F12: =(1-Assumptions!$B$18)*F7+Assumptions!$B$18*F8 -> 5.3126214 | G12: =(1-Assumptions!$B$18)*G7+Assumptions!$B$18*G8 -> 0.9220252 | H12: =(1-Assumptions!$B$18)*H7+Assumptions!$B$18*H8 -> 4.3905962 | K12: =(1-Assumptions!$B$18)*K7+Assumptions!$B$18*K8 -> 0.50065472 | L12: =(1-Assumptions!$B$18)*L7+Assumptions!$B$18*L8 -> 3.8899415 | M12: =(1-Assumptions!$B$18)*M7+Assumptions!$B$18*M8 -> 0.457864 | N12: =(1-Assumptions!$B$18)*N7+Assumptions!$B$18*N8 -> 0.02 | O12: =(1-Assumptions!$B$18)*O7+Assumptions!$B$18*O8 -> 3.4058055 | P12: =IF(F12=0,0,O12/F12) -> 0.64107815 | Q12: =(1-Assumptions!$B$18)*Q7+Assumptions!$B$18*Q8 -> 3.1218 | R12: =(1-Assumptions!$B$18)*R7+Assumptions!$B$18*R8 -> 0.74186949
A13: All payers | B13: Blended | F13: =IF((Assumptions!$B$15+Assumptions!$B$16)=0,0,Assumptions!$B$15/(Assumptions!$B$15+Assumptions!$B$16)*F11+(1-Assumptions!$B$15/(Assumptions!$B$15+Assumptions!$B$16))*F12) -> 3.5424265 | G13: =IF((Assumptions!$B$15+Assumptions!$B$16)=0,0,Assumptions!$B$15/(Assumptions!$B$15+Assumptions!$B$16)*G11+(1-Assumptions!$B$15/(Assumptions!$B$15+Assumptions!$B$16))*G12) -> 0.6148013 | H13: =IF((Assumptions!$B$15+Assumptions!$B$16)=0,0,Assumptions!$B$15/(Assumptions!$B$15+Assumptions!$B$16)*H11+(1-Assumptions!$B$15/(Assumptions!$B$15+Assumptions!$B$16))*H12) -> 2.9276252 | K13: =IF((Assumptions!$B$15+Assumptions!$B$16)=0,0,Assumptions!$B$15/(Assumptions!$B$15+Assumptions!$B$16)*K11+(1-Assumptions!$B$15/(Assumptions!$B$15+Assumptions!$B$16))*K12) -> 0.33465963 | L13: =IF((Assumptions!$B$15+Assumptions!$B$16)=0,0,Assumptions!$B$15/(Assumptions!$B$15+Assumptions!$B$16)*L11+(1-Assumptions!$B$15/(Assumptions!$B$15+Assumptions!$B$16))*L12) -> 2.5929656 | M13: =IF((Assumptions!$B$15+Assumptions!$B$16)=0,0,Assumptions!$B$15/(Assumptions!$B$15+Assumptions!$B$16)*M11+(1-Assumptions!$B$15/(Assumptions!$B$15+Assumptions!$B$16))*M12) -> 0.313126 | N13: =IF((Assumptions!$B$15+Assumptions!$B$16)=0,0,Assumptions!$B$15/(Assumptions!$B$15+Assumptions!$B$16)*N11+(1-Assumptions!$B$15/(Assumptions!$B$15+Assumptions!$B$16))*N12) -> 0.02 | O13: =IF((Assumptions!$B$15+Assumptions!$B$16)=0,0,Assumptions!$B$15/(Assumptions!$B$15+Assumptions!$B$16)*O11+(1-Assumptions!$B$15/(Assumptions!$B$15+Assumptions!$B$16))*O12) -> 2.2536718 | P13: =IF(F13=0,0,O13/F13) -> 0.63619437 | Q13: =IF((Assumptions!$B$15+Assumptions!$B$16)=0,0,Assumptions!$B$15/(Assumptions!$B$15+Assumptions!$B$16)*Q11+(1-Assumptions!$B$15/(Assumptions!$B$15+Assumptions!$B$16))*Q12) -> 2.61096 | R13: =IF((Assumptions!$B$15+Assumptions!$B$16)=0,0,Assumptions!$B$15/(Assumptions!$B$15+Assumptions!$B$16)*R11+(1-Assumptions!$B$15/(Assumptions!$B$15+Assumptions!$B$16))*R12) -> -0.044162172
A15: Where Pro annual is bought: what you keep (average regional price)
A16: Channel | C16: Price (€/yr) | D16: VAT (€) | E16: Commission / fees (€) | F16: You keep (€/yr) | G16: Share kept
A17: In-app (store) | C17: =C6 -> 31.14377 | D17: =C6-C6/(1+Assumptions!$B$7) -> 5.4051171 | E17: =C6/(1+Assumptions!$B$7)*Assumptions!$B$21 -> 3.8607979 | F17: =C17-D17-E17 -> 21.877855 | G17: =IF(C17=0,0,F17/C17) -> 0.70247934
A18: Web, VAT registered | C18: =C6 -> 31.14377 | D18: =C6-C6/(1+Assumptions!$B$7) -> 5.4051171 | E18: =C6*(Assumptions!$B$22+Assumptions!$B$24)+Assumptions!$B$23 -> 0.93516294 | F18: =C18-D18-E18 -> 24.80349 | G18: =IF(C18=0,0,F18/C18) -> 0.79641899
A19: Web, VAT-exempt (franchise) | C19: =C6 -> 31.14377 | D19: =0 -> 0 | E19: =C6*(Assumptions!$B$22+Assumptions!$B$24)+Assumptions!$B$23 -> 0.93516294 | F19: =C19-D19-E19 -> 30.208607 | G19: =IF(C19=0,0,F19/C19) -> 0.96997271
A21: Break-even (the result before social contributions and income tax)
A22: Stage | C22: Fixed costs (€/mo) | D22: Paying users needed | E22: Active users needed | F22: Contribution per active user (€/mo)
A23: Launch | C23: ='Fixed costs'!$I$24 -> 232.68245 | D23: =IF(ISNUMBER(E23),ROUNDUP(E23*(Assumptions!$B$15+Assumptions!$B$16),0),"never") -> 100 | E23: =IF(F23<=0,"never",ROUNDUP(C23/F23,0)) -> 1801 | F23: =(Assumptions!$B$15*$O$11+Assumptions!$B$16*$O$12)+(1-Assumptions!$B$15-Assumptions!$B$16)*(Assumptions!$B$54*Assumptions!$B$56*'Credit shop'!$G$22-$C$29)+Assumptions!$B$15*Assumptions!$B$55*Assumptions!$B$56*'Credit shop'!$G$22 -> 0.12922989
A24: Growth | C24: ='Fixed costs'!$J$24 -> 355.32145 | D24: =IF(ISNUMBER(E24),ROUNDUP(E24*(Assumptions!$B$15+Assumptions!$B$16),0),"never") -> 152 | E24: =IF(F24<=0,"never",ROUNDUP(C24/F24,0)) -> 2750 | F24: =(Assumptions!$B$15*$O$11+Assumptions!$B$16*$O$12)+(1-Assumptions!$B$15-Assumptions!$B$16)*(Assumptions!$B$54*Assumptions!$B$56*'Credit shop'!$G$22-$C$29)+Assumptions!$B$15*Assumptions!$B$55*Assumptions!$B$56*'Credit shop'!$G$22 -> 0.12922989
A25: Scale | C25: ='Fixed costs'!$K$24 -> 736.5767 | D25: =IF(ISNUMBER(E25),ROUNDUP(E25*(Assumptions!$B$15+Assumptions!$B$16),0),"never") -> 314 | E25: =IF(F25<=0,"never",ROUNDUP(C25/F25,0)) -> 5700 | F25: =(Assumptions!$B$15*$O$11+Assumptions!$B$16*$O$12)+(1-Assumptions!$B$15-Assumptions!$B$16)*(Assumptions!$B$54*Assumptions!$B$56*'Credit shop'!$G$22-$C$29)+Assumptions!$B$15*Assumptions!$B$55*Assumptions!$B$56*'Credit shop'!$G$22 -> 0.12922989
A27: Conservative: counts VAT on web sales. While the VAT exemption applies you keep more, so break-even comes sooner (see 'Projection'). Break-even counts every active user: the payers' margin, the credit packs, and what each free user costs, AI included.
A29: What a free user costs per month (€) | C29: =Assumptions!$B$35+C30 -> 0.030812
A30: … of which AI, expected (€) | C30: =Assumptions!$B$49*Assumptions!$B$6*(1+Assumptions!$B$8) -> 0.020812
A32: 7-day trial on the annual plans (its cost, spread over the year it buys)
A33: Trial length (days) | C33: 7
A34: Cost of one trial that does not convert: Pro / Max (€) | C34: =C33/30*(M6+N6) -> 0.070224467 | D34: =C33/30*(M8+N8) -> 0.1115016
A35: Trial cost per Pro annual payer, per month (€) | C35: =IF(Assumptions!$B$51=0,0,(1/Assumptions!$B$51-1)*C34/12) -> 0.0087780583
A36: Trial cost per Max annual payer, per month (€) | C36: =IF(Assumptions!$B$51=0,0,(1/Assumptions!$B$51-1)*D34/12) -> 0.0139377

Sheet Projection
A1: Cost and result by number of active users (steady month)
A2: Row 5 is an input: change the active-user figures · every other row is calculated.
A4: Per month | B4: Scenario 1 | C4: Scenario 2 | D4: Scenario 3 | E4: Scenario 4 | F4: Scenario 5 | G4: Scenario 6 | H4: Scenario 7 | I4: Scenario 8
A5: Monthly active users (MAU) | B5: 100 | C5: 500 | D5: 1000 | E5: 2500 | F5: 5000 | G5: 10000 | H5: 25000 | I5: 50000
A6: Stage (1 Launch · 2 Growth · 3 Scale) | B6: =IF(B5>=Assumptions!$B$39,3,IF(B5>=Assumptions!$B$38,2,1)) -> 1 | C6: =IF(C5>=Assumptions!$B$39,3,IF(C5>=Assumptions!$B$38,2,1)) -> 1 | D6: =IF(D5>=Assumptions!$B$39,3,IF(D5>=Assumptions!$B$38,2,1)) -> 1 | E6: =IF(E5>=Assumptions!$B$39,3,IF(E5>=Assumptions!$B$38,2,1)) -> 2 | F6: =IF(F5>=Assumptions!$B$39,3,IF(F5>=Assumptions!$B$38,2,1)) -> 2 | G6: =IF(G5>=Assumptions!$B$39,3,IF(G5>=Assumptions!$B$38,2,1)) -> 2 | H6: =IF(H5>=Assumptions!$B$39,3,IF(H5>=Assumptions!$B$38,2,1)) -> 3 | I6: =IF(I5>=Assumptions!$B$39,3,IF(I5>=Assumptions!$B$38,2,1)) -> 3
A7: Free users | B7: =B5-B8-B9 -> 94 | C7: =C5-C8-C9 -> 472 | D7: =D5-D8-D9 -> 945 | E7: =E5-E8-E9 -> 2362 | F7: =F5-F8-F9 -> 4725 | G7: =G5-G8-G9 -> 9450 | H7: =H5-H8-H9 -> 23625 | I7: =I5-I8-I9 -> 47250
A8: Pro subscribers | B8: =ROUND(B5*Assumptions!$B$15,0) -> 5 | C8: =ROUND(C5*Assumptions!$B$15,0) -> 23 | D8: =ROUND(D5*Assumptions!$B$15,0) -> 45 | E8: =ROUND(E5*Assumptions!$B$15,0) -> 113 | F8: =ROUND(F5*Assumptions!$B$15,0) -> 225 | G8: =ROUND(G5*Assumptions!$B$15,0) -> 450 | H8: =ROUND(H5*Assumptions!$B$15,0) -> 1125 | I8: =ROUND(I5*Assumptions!$B$15,0) -> 2250
A9: Max subscribers | B9: =ROUND(B5*Assumptions!$B$16,0) -> 1 | C9: =ROUND(C5*Assumptions!$B$16,0) -> 5 | D9: =ROUND(D5*Assumptions!$B$16,0) -> 10 | E9: =ROUND(E5*Assumptions!$B$16,0) -> 25 | F9: =ROUND(F5*Assumptions!$B$16,0) -> 50 | G9: =ROUND(G5*Assumptions!$B$16,0) -> 100 | H9: =ROUND(H5*Assumptions!$B$16,0) -> 250 | I9: =ROUND(I5*Assumptions!$B$16,0) -> 500
A10: Paying users, total | B10: =B8+B9 -> 6 | C10: =C8+C9 -> 28 | D10: =D8+D9 -> 55 | E10: =E8+E9 -> 138 | F10: =F8+F9 -> 275 | G10: =G8+G9 -> 550 | H10: =H8+H9 -> 1375 | I10: =I8+I9 -> 2750
A11: Credit pack buyers | B11: =ROUND(B7*Assumptions!$B$54+B8*Assumptions!$B$55,0) -> 1 | C11: =ROUND(C7*Assumptions!$B$54+C8*Assumptions!$B$55,0) -> 6 | D11: =ROUND(D7*Assumptions!$B$54+D8*Assumptions!$B$55,0) -> 12 | E11: =ROUND(E7*Assumptions!$B$54+E8*Assumptions!$B$55,0) -> 29 | F11: =ROUND(F7*Assumptions!$B$54+F8*Assumptions!$B$55,0) -> 59 | G11: =ROUND(G7*Assumptions!$B$54+G8*Assumptions!$B$55,0) -> 117 | H11: =ROUND(H7*Assumptions!$B$54+H8*Assumptions!$B$55,0) -> 293 | I11: =ROUND(I7*Assumptions!$B$54+I8*Assumptions!$B$55,0) -> 585
A12: REVENUE
A13: Gross subscription billings incl. VAT | B13: =B8*'Unit economics'!$F$11+B9*'Unit economics'!$F$12 -> 21.057871 | C13: =C8*'Unit economics'!$F$11+C9*'Unit economics'!$F$12 -> 98.991255 | D13: =D8*'Unit economics'!$F$11+D9*'Unit economics'!$F$12 -> 194.83346 | E13: =E8*'Unit economics'!$F$11+E9*'Unit economics'!$F$12 -> 488.65817 | F13: =F8*'Unit economics'!$F$11+F9*'Unit economics'!$F$12 -> 974.1673 | G13: =G8*'Unit economics'!$F$11+G9*'Unit economics'!$F$12 -> 1948.3346 | H13: =H8*'Unit economics'!$F$11+H9*'Unit economics'!$F$12 -> 4870.8365 | I13: =I8*'Unit economics'!$F$11+I9*'Unit economics'!$F$12 -> 9741.673
A14: − VAT (paid to the state, or kept by the store) | B14: =-(B8*'Unit economics'!$G$11+B9*'Unit economics'!$G$12) -> -3.6546718 | C14: =-(C8*'Unit economics'!$G$11+C9*'Unit economics'!$G$12) -> -17.1803 | D14: =-(D8*'Unit economics'!$G$11+D9*'Unit economics'!$G$12) -> -33.814072 | E14: =-(E8*'Unit economics'!$G$11+E9*'Unit economics'!$G$12) -> -84.808444 | F14: =-(F8*'Unit economics'!$G$11+F9*'Unit economics'!$G$12) -> -169.07036 | G14: =-(G8*'Unit economics'!$G$11+G9*'Unit economics'!$G$12) -> -338.14072 | H14: =-(H8*'Unit economics'!$G$11+H9*'Unit economics'!$G$12) -> -845.35179 | I14: =-(I8*'Unit economics'!$G$11+I9*'Unit economics'!$G$12) -> -1690.7036
A15: + VAT not charged on web sales (exemption) | B15: =B23*(1-Assumptions!$B$19)*(B8*'Unit economics'!$G$11+B9*'Unit economics'!$G$12) -> 1.4618687 | C15: =C23*(1-Assumptions!$B$19)*(C8*'Unit economics'!$G$11+C9*'Unit economics'!$G$12) -> 6.8721202 | D15: =D23*(1-Assumptions!$B$19)*(D8*'Unit economics'!$G$11+D9*'Unit economics'!$G$12) -> 13.525629 | E15: =E23*(1-Assumptions!$B$19)*(E8*'Unit economics'!$G$11+E9*'Unit economics'!$G$12) -> 33.923377 | F15: =F23*(1-Assumptions!$B$19)*(F8*'Unit economics'!$G$11+F9*'Unit economics'!$G$12) -> 67.628143 | G15: =G23*(1-Assumptions!$B$19)*(G8*'Unit economics'!$G$11+G9*'Unit economics'!$G$12) -> 135.25629 | H15: =H23*(1-Assumptions!$B$19)*(H8*'Unit economics'!$G$11+H9*'Unit economics'!$G$12) -> 0 | I15: =I23*(1-Assumptions!$B$19)*(I8*'Unit economics'!$G$11+I9*'Unit economics'!$G$12) -> 0
A16: − Store commission and payment fees | B16: =-(B8*'Unit economics'!$K$11+B9*'Unit economics'!$K$12) -> -1.9895139 | C16: =-(C8*'Unit economics'!$K$11+C9*'Unit economics'!$K$12) -> -9.3520256 | D16: =-(D8*'Unit economics'!$K$11+D9*'Unit economics'!$K$12) -> -18.406279 | E16: =-(E8*'Unit economics'!$K$11+E9*'Unit economics'!$K$12) -> -46.164584 | F16: =-(F8*'Unit economics'!$K$11+F9*'Unit economics'!$K$12) -> -92.031397 | G16: =-(G8*'Unit economics'!$K$11+G9*'Unit economics'!$K$12) -> -184.06279 | H16: =-(H8*'Unit economics'!$K$11+H9*'Unit economics'!$K$12) -> -460.15699 | I16: =-(I8*'Unit economics'!$K$11+I9*'Unit economics'!$K$12) -> -920.31397
A17: + Credit packs, net of VAT and fees | B17: =B11*Assumptions!$B$56*'Credit shop'!$G$22 -> 2.9397678 | C17: =C11*Assumptions!$B$56*'Credit shop'!$G$22 -> 17.638607 | D17: =D11*Assumptions!$B$56*'Credit shop'!$G$22 -> 35.277213 | E17: =E11*Assumptions!$B$56*'Credit shop'!$G$22 -> 85.253265 | F17: =F11*Assumptions!$B$56*'Credit shop'!$G$22 -> 173.4463 | G17: =G11*Assumptions!$B$56*'Credit shop'!$G$22 -> 343.95283 | H17: =H11*Assumptions!$B$56*'Credit shop'!$G$22 -> 861.35195 | I17: =I11*Assumptions!$B$56*'Credit shop'!$G$22 -> 1719.7641
A18: Net revenue | B18: =SUM(B13:B17) -> 19.815322 | C18: =SUM(C13:C17) -> 96.969656 | D18: =SUM(D13:D17) -> 191.41595 | E18: =SUM(E13:E17) -> 476.86179 | F18: =SUM(F13:F17) -> 954.13999 | G18: =SUM(G13:G17) -> 1905.3402 | H18: =SUM(H13:H17) -> 4426.6797 | I18: =SUM(I13:I17) -> 8850.4196
A20: VAT EXEMPTION CHECK
A21: Turnover per year (excl. VAT) | B21: =(B13+B14+B11*Assumptions!$B$56*'Credit shop'!$C$21/(1+Assumptions!$B$7))*12 -> 249.18219 | C21: =(C13+C14+C11*Assumptions!$B$56*'Credit shop'!$C$21/(1+Assumptions!$B$7))*12 -> 1223.7943 | D21: =(D13+D14+D11*Assumptions!$B$56*'Credit shop'!$C$21/(1+Assumptions!$B$7))*12 -> 2416.3583 | E21: =(E13+E14+E11*Assumptions!$B$56*'Credit shop'!$C$21/(1+Assumptions!$B$7))*12 -> 6016.167 | F21: =(F13+F14+F11*Assumptions!$B$56*'Credit shop'!$C$21/(1+Assumptions!$B$7))*12 -> 12041.448 | G21: =(G13+G14+G11*Assumptions!$B$56*'Credit shop'!$C$21/(1+Assumptions!$B$7))*12 -> 24042.551 | H21: =(H13+H14+H11*Assumptions!$B$56*'Credit shop'!$C$21/(1+Assumptions!$B$7))*12 -> 60126.55 | I21: =(I13+I14+I11*Assumptions!$B$56*'Credit shop'!$C$21/(1+Assumptions!$B$7))*12 -> 120212.76
A22: Web sales to other EU countries per year | B22: =(B13*(1-Assumptions!$B$19)+B11*Assumptions!$B$56*'Credit shop'!$C$21*(1-Assumptions!$B$58))*Assumptions!$B$29*12 -> 84.767504 | C22: =(C13*(1-Assumptions!$B$19)+C11*Assumptions!$B$56*'Credit shop'!$C$21*(1-Assumptions!$B$58))*Assumptions!$B$29*12 -> 403.5581 | D22: =(D13*(1-Assumptions!$B$19)+D11*Assumptions!$B$56*'Credit shop'!$C$21*(1-Assumptions!$B$58))*Assumptions!$B$29*12 -> 795.02385 | E22: =(E13*(1-Assumptions!$B$19)+E11*Assumptions!$B$56*'Credit shop'!$C$21*(1-Assumptions!$B$58))*Assumptions!$B$29*12 -> 1989.7005 | F22: =(F13*(1-Assumptions!$B$19)+F11*Assumptions!$B$56*'Credit shop'!$C$21*(1-Assumptions!$B$58))*Assumptions!$B$29*12 -> 3971.214 | G22: =(G13*(1-Assumptions!$B$19)+G11*Assumptions!$B$56*'Credit shop'!$C$21*(1-Assumptions!$B$58))*Assumptions!$B$29*12 -> 7938.5226 | H22: =(H13*(1-Assumptions!$B$19)+H11*Assumptions!$B$56*'Credit shop'!$C$21*(1-Assumptions!$B$58))*Assumptions!$B$29*12 -> 19848.259 | I22: =(I13*(1-Assumptions!$B$19)+I11*Assumptions!$B$56*'Credit shop'!$C$21*(1-Assumptions!$B$58))*Assumptions!$B$29*12 -> 39692.613
A23: Exemption applies? (1 = yes) | B23: =IF(AND(Assumptions!$B$26="Y",B21<=Assumptions!$B$27,B22<=Assumptions!$B$28),1,0) -> 1 | C23: =IF(AND(Assumptions!$B$26="Y",C21<=Assumptions!$B$27,C22<=Assumptions!$B$28),1,0) -> 1 | D23: =IF(AND(Assumptions!$B$26="Y",D21<=Assumptions!$B$27,D22<=Assumptions!$B$28),1,0) -> 1 | E23: =IF(AND(Assumptions!$B$26="Y",E21<=Assumptions!$B$27,E22<=Assumptions!$B$28),1,0) -> 1 | F23: =IF(AND(Assumptions!$B$26="Y",F21<=Assumptions!$B$27,F22<=Assumptions!$B$28),1,0) -> 1 | G23: =IF(AND(Assumptions!$B$26="Y",G21<=Assumptions!$B$27,G22<=Assumptions!$B$28),1,0) -> 1 | H23: =IF(AND(Assumptions!$B$26="Y",H21<=Assumptions!$B$27,H22<=Assumptions!$B$28),1,0) -> 0 | I23: =IF(AND(Assumptions!$B$26="Y",I21<=Assumptions!$B$27,I22<=Assumptions!$B$28),1,0) -> 0
A25: COSTS
A26: AI, expected (payers and free users) | B26: =B8*'Unit economics'!$M$11+B9*'Unit economics'!$M$12+B7*'Unit economics'!$C$30 -> 3.819002 | C26: =C8*'Unit economics'!$M$11+C9*'Unit economics'!$M$12+C7*'Unit economics'!$C$30 -> 18.57471 | D26: =D8*'Unit economics'!$M$11+D9*'Unit economics'!$M$12+D7*'Unit economics'!$C$30 -> 36.88927 | E26: =E8*'Unit economics'!$M$11+E9*'Unit economics'!$M$12+E7*'Unit economics'!$C$30 -> 92.35325 | F26: =F8*'Unit economics'!$M$11+F9*'Unit economics'!$M$12+F7*'Unit economics'!$C$30 -> 184.44635 | G26: =G8*'Unit economics'!$M$11+G9*'Unit economics'!$M$12+G7*'Unit economics'!$C$30 -> 368.8927 | H26: =H8*'Unit economics'!$M$11+H9*'Unit economics'!$M$12+H7*'Unit economics'!$C$30 -> 922.23175 | I26: =I8*'Unit economics'!$M$11+I9*'Unit economics'!$M$12+I7*'Unit economics'!$C$30 -> 1844.4635
A27: Variable infrastructure | B27: =B7*Assumptions!$B$35+B10*Assumptions!$B$36 -> 1.06 | C27: =C7*Assumptions!$B$35+C10*Assumptions!$B$36 -> 5.28 | D27: =D7*Assumptions!$B$35+D10*Assumptions!$B$36 -> 10.55 | E27: =E7*Assumptions!$B$35+E10*Assumptions!$B$36 -> 26.38 | F27: =F7*Assumptions!$B$35+F10*Assumptions!$B$36 -> 52.75 | G27: =G7*Assumptions!$B$35+G10*Assumptions!$B$36 -> 105.5 | H27: =H7*Assumptions!$B$35+H10*Assumptions!$B$36 -> 263.75 | I27: =I7*Assumptions!$B$35+I10*Assumptions!$B$36 -> 527.5
A28: Fixed costs (by stage) | B28: =CHOOSE(B6,'Fixed costs'!$I$24,'Fixed costs'!$J$24,'Fixed costs'!$K$24) -> 232.68245 | C28: =CHOOSE(C6,'Fixed costs'!$I$24,'Fixed costs'!$J$24,'Fixed costs'!$K$24) -> 232.68245 | D28: =CHOOSE(D6,'Fixed costs'!$I$24,'Fixed costs'!$J$24,'Fixed costs'!$K$24) -> 232.68245 | E28: =CHOOSE(E6,'Fixed costs'!$I$24,'Fixed costs'!$J$24,'Fixed costs'!$K$24) -> 355.32145 | F28: =CHOOSE(F6,'Fixed costs'!$I$24,'Fixed costs'!$J$24,'Fixed costs'!$K$24) -> 355.32145 | G28: =CHOOSE(G6,'Fixed costs'!$I$24,'Fixed costs'!$J$24,'Fixed costs'!$K$24) -> 355.32145 | H28: =CHOOSE(H6,'Fixed costs'!$I$24,'Fixed costs'!$J$24,'Fixed costs'!$K$24) -> 736.5767 | I28: =CHOOSE(I6,'Fixed costs'!$I$24,'Fixed costs'!$J$24,'Fixed costs'!$K$24) -> 736.5767
A29: Total operating costs | B29: =B26+B27+B28 -> 237.56145 | C29: =C26+C27+C28 -> 256.53716 | D29: =D26+D27+D28 -> 280.12172 | E29: =E26+E27+E28 -> 474.0547 | F29: =F26+F27+F28 -> 592.5178 | G29: =G26+G27+G28 -> 829.71415 | H29: =H26+H27+H28 -> 1922.5584 | I29: =I26+I27+I28 -> 3108.5402
A31: RESULT
A32: Operating result (before social contributions) | B32: =B18-B29 -> -217.74613 | C32: =C18-C29 -> -159.5675 | D32: =D18-D29 -> -88.705769 | E32: =E18-E29 -> 2.8070893 | F32: =F18-F29 -> 361.62219 | G32: =G18-G29 -> 1075.6261 | H32: =H18-H29 -> 2504.1212 | I32: =I18-I29 -> 5741.8794
A33: Profit per year (basis for social contributions) | B33: =MAX(0,B32)*12 -> 0 | C33: =MAX(0,C32)*12 -> 0 | D33: =MAX(0,D32)*12 -> 0 | E33: =MAX(0,E32)*12 -> 33.685071 | F33: =MAX(0,F32)*12 -> 4339.4662 | G33: =MAX(0,G32)*12 -> 12907.513 | H33: =MAX(0,H32)*12 -> 30049.455 | I33: =MAX(0,I32)*12 -> 68902.553
A34: Social contributions, student self-employed | B34: =IF(B33<=Assumptions!$B$41,0,IF(B33<Assumptions!$B$42,Assumptions!$B$43*(B33-Assumptions!$B$41),MAX(4*Assumptions!$B$44,Assumptions!$B$43*B33)))/12 -> 0 | C34: =IF(C33<=Assumptions!$B$41,0,IF(C33<Assumptions!$B$42,Assumptions!$B$43*(C33-Assumptions!$B$41),MAX(4*Assumptions!$B$44,Assumptions!$B$43*C33)))/12 -> 0 | D34: =IF(D33<=Assumptions!$B$41,0,IF(D33<Assumptions!$B$42,Assumptions!$B$43*(D33-Assumptions!$B$41),MAX(4*Assumptions!$B$44,Assumptions!$B$43*D33)))/12 -> 0 | E34: =IF(E33<=Assumptions!$B$41,0,IF(E33<Assumptions!$B$42,Assumptions!$B$43*(E33-Assumptions!$B$41),MAX(4*Assumptions!$B$44,Assumptions!$B$43*E33)))/12 -> 0 | F34: =IF(F33<=Assumptions!$B$41,0,IF(F33<Assumptions!$B$42,Assumptions!$B$43*(F33-Assumptions!$B$41),MAX(4*Assumptions!$B$44,Assumptions!$B$43*F33)))/12 -> 0 | G34: =IF(G33<=Assumptions!$B$41,0,IF(G33<Assumptions!$B$42,Assumptions!$B$43*(G33-Assumptions!$B$41),MAX(4*Assumptions!$B$44,Assumptions!$B$43*G33)))/12 -> 72.099741 | H34: =IF(H33<=Assumptions!$B$41,0,IF(H33<Assumptions!$B$42,Assumptions!$B$43*(H33-Assumptions!$B$41),MAX(4*Assumptions!$B$44,Assumptions!$B$43*H33)))/12 -> 513.34485 | I34: =IF(I33<=Assumptions!$B$41,0,IF(I33<Assumptions!$B$42,Assumptions!$B$43*(I33-Assumptions!$B$41),MAX(4*Assumptions!$B$44,Assumptions!$B$43*I33)))/12 -> 1177.0853
A35: Result after social contributions (before income tax) | B35: =B32-B34 -> -217.74613 | C35: =C32-C34 -> -159.5675 | D35: =D32-D34 -> -88.705769 | E35: =E32-E34 -> 2.8070893 | F35: =F32-F34 -> 361.62219 | G35: =G32-G34 -> 1003.5263 | H35: =H32-H34 -> 1990.7764 | I35: =I32-I34 -> 4564.7941
A36: Result over 12 months | B36: =B35*12 -> -2612.9536 | C36: =C35*12 -> -1914.8101 | D36: =D35*12 -> -1064.4692 | E36: =E35*12 -> 33.685071 | F36: =F35*12 -> 4339.4662 | G36: =G35*12 -> 12042.316 | H36: =H35*12 -> 23889.317 | I36: =I35*12 -> 54777.529
A37: Still within the student status? (profit < limit) | B37: =IF(B33<Assumptions!$B$42,"yes","no: full-time rates") -> yes | C37: =IF(C33<Assumptions!$B$42,"yes","no: full-time rates") -> yes | D37: =IF(D33<Assumptions!$B$42,"yes","no: full-time rates") -> yes | E37: =IF(E33<Assumptions!$B$42,"yes","no: full-time rates") -> yes | F37: =IF(F33<Assumptions!$B$42,"yes","no: full-time rates") -> yes | G37: =IF(G33<Assumptions!$B$42,"yes","no: full-time rates") -> yes | H37: =IF(H33<Assumptions!$B$42,"yes","no: full-time rates") -> no: full-time rates | I37: =IF(I33<Assumptions!$B$42,"yes","no: full-time rates") -> no: full-time rates
A39: COST PER USER
A40: Total cost per active user | B40: =IF(B5=0,0,B29/B5) -> 2.3756145 | C40: =IF(C5=0,0,C29/C5) -> 0.51307432 | D40: =IF(D5=0,0,D29/D5) -> 0.28012172 | E40: =IF(E5=0,0,E29/E5) -> 0.18962188 | F40: =IF(F5=0,0,F29/F5) -> 0.11850356 | G40: =IF(G5=0,0,G29/G5) -> 0.082971415 | H40: =IF(H5=0,0,H29/H5) -> 0.076902338 | I40: =IF(I5=0,0,I29/I5) -> 0.062170804
A41: Total cost per paying user | B41: =IF(B10=0,0,B29/B10) -> 39.593575 | C41: =IF(C10=0,0,C29/C10) -> 9.1620414 | D41: =IF(D10=0,0,D29/D10) -> 5.0931222 | E41: =IF(E10=0,0,E29/E10) -> 3.435179 | F41: =IF(F10=0,0,F29/F10) -> 2.1546102 | G41: =IF(G10=0,0,G29/G10) -> 1.5085712 | H41: =IF(H10=0,0,H29/H10) -> 1.3982243 | I41: =IF(I10=0,0,I29/I10) -> 1.1303783
A42: Net revenue per paying user | B42: =IF(B10=0,0,B18/B10) -> 3.3025536 | C42: =IF(C10=0,0,C18/C10) -> 3.463202 | D42: =IF(D10=0,0,D18/D10) -> 3.48029 | E42: =IF(E10=0,0,E18/E10) -> 3.4555202 | F42: =IF(F10=0,0,F18/F10) -> 3.4695999 | G42: =IF(G10=0,0,G18/G10) -> 3.4642549 | H42: =IF(H10=0,0,H18/H10) -> 3.2194034 | I42: =IF(I10=0,0,I18/I10) -> 3.2183344
A43: Variable cost of one free user | B43: ='Unit economics'!$C$29 -> 0.030812 | C43: ='Unit economics'!$C$29 -> 0.030812 | D43: ='Unit economics'!$C$29 -> 0.030812 | E43: ='Unit economics'!$C$29 -> 0.030812 | F43: ='Unit economics'!$C$29 -> 0.030812 | G43: ='Unit economics'!$C$29 -> 0.030812 | H43: ='Unit economics'!$C$29 -> 0.030812 | I43: ='Unit economics'!$C$29 -> 0.030812
A44: Operating margin (% of net revenue) | B44: =IF(B18=0,0,B32/B18) -> -10.988776 | C44: =IF(C18=0,0,C32/C18) -> -1.6455406 | D44: =IF(D18=0,0,D32/D18) -> -0.4634189 | E44: =IF(E18=0,0,E32/E18) -> 0.0058865888 | F44: =IF(F18=0,0,F32/F18) -> 0.37900328 | G44: =IF(G18=0,0,G32/G18) -> 0.56453228 | H44: =IF(H18=0,0,H32/H18) -> 0.56568837 | I44: =IF(I18=0,0,I32/I18) -> 0.64876917
A46: STRESS TEST
A47: AI if every payer hits the worst case | B47: =B8*'Unit economics'!$Q$11+B9*'Unit economics'!$Q$12 -> 15.609 | C47: =C8*'Unit economics'!$Q$11+C9*'Unit economics'!$Q$12 -> 73.05012 | D47: =D8*'Unit economics'!$Q$11+D9*'Unit economics'!$Q$12 -> 143.6028 | E47: =E8*'Unit economics'!$Q$11+E9*'Unit economics'!$Q$12 -> 360.25572 | F47: =F8*'Unit economics'!$Q$11+F9*'Unit economics'!$Q$12 -> 718.014 | G47: =G8*'Unit economics'!$Q$11+G9*'Unit economics'!$Q$12 -> 1436.028 | H47: =H8*'Unit economics'!$Q$11+H9*'Unit economics'!$Q$12 -> 3590.07 | I47: =I8*'Unit economics'!$Q$11+I9*'Unit economics'!$Q$12 -> 7180.14
A48: AI if every free user hits the free worst case | B48: =B7*Assumptions!$B$50*Assumptions!$B$6*(1+Assumptions!$B$8) -> 29.34492 | C48: =C7*Assumptions!$B$50*Assumptions!$B$6*(1+Assumptions!$B$8) -> 147.34896 | D48: =D7*Assumptions!$B$50*Assumptions!$B$6*(1+Assumptions!$B$8) -> 295.0101 | E48: =E7*Assumptions!$B$50*Assumptions!$B$6*(1+Assumptions!$B$8) -> 737.36916 | F48: =F7*Assumptions!$B$50*Assumptions!$B$6*(1+Assumptions!$B$8) -> 1475.0505 | G48: =G7*Assumptions!$B$50*Assumptions!$B$6*(1+Assumptions!$B$8) -> 2950.101 | H48: =H7*Assumptions!$B$50*Assumptions!$B$6*(1+Assumptions!$B$8) -> 7375.2525 | I48: =I7*Assumptions!$B$50*Assumptions!$B$6*(1+Assumptions!$B$8) -> 14750.505
A49: Operating result, worst-case AI for everyone | B49: =B18-(B47+B48+B27+B28) -> -258.88105 | C49: =C18-(C47+C48+C27+C28) -> -361.39187 | D49: =D18-(D47+D48+D27+D28) -> -490.4294 | E49: =E18-(E47+E48+E27+E28) -> -1002.4645 | F49: =F18-(F47+F48+F27+F28) -> -1646.996 | G49: =G18-(G47+G48+G27+G28) -> -2941.6102 | H49: =H18-(H47+H48+H27+H28) -> -7538.9695 | I49: =I18-(I47+I48+I27+I28) -> -14344.302
A51: Social contributions follow the 2026 student self-employed rules: nothing up to €8,687 of yearly profit, 20.5% of the part above it, and full-time rates (minimum €925.59 a quarter) from €17,374.
A52: Once the exemption stops applying (turnover over €25,000, or over €10,000 of web sales abroad), you must register for VAT normally: then set 'VAT you pay on services bought abroad' to 0%.
A53: Steady-state snapshot: churn and growth over time are not modelled. The founder discount applies to the share of annual payers set in Assumptions; trials are costed in 'Unit economics'. Income tax is not included.

Sheet Offer review
A1: The offer as decided (26 Oct 2026), compared with the code today
A2: 'Today in the code' = the limits currently set in the repository (backend/core/credits.py, routes/*). 'e.g.' = a proposal still to confirm.
A4: Feature | B4: Free | C4: Pro | D4: Max | E4: Today in the code | F4: Status / still to decide
A5: Price (tier 1) | B5: €0 | C5: €4.99 / month · €49.99 / year | D5: €7.99 / month · €59.99 / year | E5: No purchase flow (HAS_STORE = false); credits not enforced (CREDITS_ENFORCE unset). | F5: Decided. Open: Max annual only €10 above Pro annual ('Pricing').
A6: Name | B6: Free · e.g. 普通 (Local) | C6: Pro · e.g. 快速 (Rapid) | D6: Max · e.g. 特急 (Limited express) | E6: The code says 'pass'; credits are 回数券. | F6: The owner likes the rail names: pick the three and how they print.
A7: Credit refill | B7: 60 a day; the refill stops at 90 | C7: 120 a day; the refill stops at 200 | D7: Unlimited | E7: 30 a day (one every 48 min), cap 50. | F7: Decided. Earned and bought credits go above the limit and never expire.
A8: Welcome | B8: Card filled to its limit on entry; bonus after the tutorial | C8: Same | D8: — | E8: 200 credits on the first read. | F8: Decided. Bonus amount to set.
A9: Due reviews | B9: 1 credit | C9: Free | D9: Free | E9: 1 credit a review; kana free. | F9: Decided.
A10: Kana | B10: 1 credit a new card, reviews free (to confirm) | C10: Same | D10: Included | E10: Kana rides free (FREE_SOURCES). | F10: To confirm.
A11: New cards (vocab, kanji, grammar) | B11: e.g. 1 credit | C11: e.g. 1 credit | D11: Included | E11: 1 credit a review. | F11: Open: what Pro spends its credits on.
A12: Practice modes | B12: 2 to 5 credits by mode; free inside a mission | C12: Same | D12: Included | E12: Pass only; practice never spends credits. | F12: Decided. The price per mode to set.
A13: Solo games (end Nov 2026) | B13: Credits | C13: Credits | D13: Included | E13: Not built. | F13: Price per game to set.
A14: PvP: async duels, real time between friends, friends list | B14: Score free; details and corrections in credits | C14: Same | D14: Included | E14: Beta this week. | F14: Open: does a duel itself cost credits? No chat for now.
A15: Missions (daily, weekly), achievements | B15: Credits + XP | C15: Credits + XP | D15: XP + status cosmetics | E15: Not built (the day_clear bonus exists). | F15: Catalogue in docs/business/strategie-monetisation.md.
... A18: AI features | B18: Small daily caps | C18: Daily caps + a ceiling ('AI worst case') | D18: Fair-use caps + a ceiling | E18: Pass only; one cap per feature in routes/*. | F18: Decided: caps per plan and a global ceiling, scaled by tier.
A19: Mock exams | B19: Pool papers | C19: Pool + 2 new a month | D19: Pool + 4 new a month | E19: Pass only; 5 new papers a day.
A20: Decks | B20: e.g. 10 private decks × 200 cards | C20: e.g. 30 × 400 | D20: e.g. 100 × 10,000, more on request | E20: Free 7 / 200; pass 100 / 10,000. | F20: Fair use, broad. Proposal: published decks with followers do not count.
A21: Analyser history | B21: e.g. 30 | C21: e.g. 100 | D21: e.g. 1,000 | E21: 30 for everyone (HISTORY_LIMIT). | F21: Numbers to set.
A22: Credit packs | B22: Yes | C22: Yes | D22: Hidden | E22: Not built. | F22: 4 packs, bigger bonus on bigger packs ('Credit shop').
A23: Trial | B23: — | C23: 7 days, annual only | D23: 7 days, annual only | E23: — | F23: Decided.
A24: Founder offer | B24: — | C24: e.g. −30% first year, annual | D24: e.g. −30% first year, annual | E24: — | F24: Decided in principle. In-app it loses on the worst case; on the web it holds ('Pricing').
A25: Gift subscriptions | B25: — | C25: 1 or 12 months | D25: 1 or 12 months | E25: Not built. | F25: Planned. Sold on the web, redeemed by code in the app.
A26: Classes (teachers) | B26: — | C26: Student seats | D26: Teacher seat | E26: Not built. | F26: Planned. Price per seat to set.
A27: Downgrade | B27: — | C27: 30-day grace; nothing deleted, over-limit decks read-only | D27: Down to Pro's limits | E27: Deck CSV export exists. | F27: Decided.
A28: Regional prices | B28: — | C28: 4 tiers, 45% to 100% | D28: 4 tiers, 45% to 100% | E28: Not built. | F28: Decided.
A30: Still to do or check
A31: 1 | B31: Legal texts: terms of sale for subscriptions and credits (the 14-day withdrawal right, waived on use with consent; renewal reminders; one-click cancel), the fair-use policy, the rules of missions, referral and the founder offer.
A32: 2 | B32: EU principles on in-game currencies: the € price beside every credit amount, no pressure selling, packs that match prices. Belgium: no paid randomness, every reward fixed.
A33: 3 | B33: Build before charging: the payment flow (stores + Stripe), the AI caps per plan and the ceiling, credits enforcement, the missions.
A34: 4 | B34: Account deletion erases friends, duels, referrals and missions (each new table in DELETE /api/account, closed to the Data API).
A35: 5 | B35: Student status and your family: income from the activity can change whether you're still a dependent for tax, and your family allowance. Check with your fund.
A36: 6 | B36: Past €17,374 of profit a year you pay full-time rates; past €25,000 of turnover, or €10,000 of web sales abroad, you register for VAT. 'Projection' flags both.
